{
  "category": "健康保険",
  "count": 7,
  "news": [
    {
      "id": "1eae114b7e2e",
      "title": "だから「終わるはずの子育て」が70年続いた…90代母に70代「ひきこもり息子」が放った強烈な一言…の多くが、「私たちの年金だけで、この先、何十年もこの子を養っていけるのだろうか」という切実な不安を口にされます。お子さんの国民年金や健康保険料、日々の…プレジデントオンラインライフ総合1/31(土) 20:15",
      "url": "https://news.yahoo.co.jp/articles/aac9e66758d86c7beb3c3f8e85da1d78c556f4c3",
      "source": "Yahoo!ニュース",
      "category": "健康保険",
      "summary": "【健康保険】 だから「終わるはずの子育て」が70年続いた…90代母に70代... (1000万円)",
      "importance": "中",
      "published_date": null,
      "scraped_at": "2026-01-31T19:16:07.817006",
      "keywords": [
        "1000万円"
      ],
      "related_categories": [],
      "content_length": 1191,
      "confidence_score": 0.26666666666666666
    },
    {
      "id": "1fafd04a9645",
      "title": "「協会けんぽ」に加入し“月額2万4000円程度”の保険料を納める私。対して「日本郵船」に勤める友人は保険料率が“たった6％”の様子。同じ月収40万円だと“年間16万円以上”も差がつく？…の方 全国健康保険協会 令和6年3月分（4月納付分）からの健康保険・厚生年金保険の保険料額表（東京都） 日本郵船健康保険組合 健康保険・介護保険の標準報酬・保険料額表…ファイナンシャルフィールド経済総合1/31(土) 17:10",
      "url": "https://news.yahoo.co.jp/articles/072a6dea79ce5e8c9e9b498cf5cf0664a4688a42",
      "source": "Yahoo!ニュース",
      "category": "健康保険",
      "summary": "【健康保険】 「協会けんぽ」に加入し“月額2万4000円程度”の保険料を納... (3739円, 40万円)",
      "importance": "低",
      "published_date": null,
      "scraped_at": "2026-01-31T19:16:12.853605",
      "keywords": [
        "協会けんぽ",
        "3739円",
        "40万円",
        "4000円",
        "16万円",
        "健康保険組合",
        "6年3月"
      ],
      "related_categories": [
        "厚生年金",
        "介護保険",
        "社会保険全般"
      ],
      "content_length": 1371,
      "confidence_score": 1.0
    },
    {
      "id": "60e5c0ab143d",
      "title": "キム・テヒ、実姉が健康保険料滞納で3億円超マンションの差し押さえも？報道にコメント…アは国民健康保険公団が昨年12月29日、キム・ヒウォン氏（ルアアセット代表）が所有するソウル城東（ソンドン）区所在のマンション1世帯を健康保険料滞納で…Kstyleアジア・韓流1/31(土) 18:03",
      "url": "https://news.yahoo.co.jp/articles/6c2f2eee82de36320fcd9b421cf706329addf298",
      "source": "Yahoo!ニュース",
      "category": "健康保険",
      "summary": "【健康保険】 キム・テヒ、実姉が健康保険料滞納で3億円超マンションの差し押... [12月29日]",
      "importance": "中",
      "published_date": null,
      "scraped_at": "2026-01-31T19:16:17.864055",
      "keywords": [],
      "related_categories": [],
      "content_length": 603,
      "confidence_score": 0.9333333333333332
    },
    {
      "id": "1d1082cbcfae",
      "title": "【衆院選・新潟4区】中道改革連合・米山隆一氏 安心できる社会保障制度の構築・物価高対策など訴え「政治を変えれば未来を作れる」…あってそれぞれ違う、おかしいでしょ?保険組合を1個にするんです。 日本健康保険組合を作って、そこがちゃんと責任を持って各都道府県に人口割でみんな同じよ…新潟ニュースNST新潟1/31(土) 18:00",
      "url": "https://news.yahoo.co.jp/articles/9578028af71b8b327e48a7a623daaba45c9b8cbf",
      "source": "Yahoo!ニュース",
      "category": "健康保険",
      "summary": "【健康保険】 【衆院選・新潟4区】中道改革連合・米山隆一氏 安心できる社会... (10%, 0%) [1月27日]",
      "importance": "低",
      "published_date": null,
      "scraped_at": "2026-01-31T19:16:20.393372",
      "keywords": [
        "10%",
        "健康保険組合",
        "0%",
        "30%"
      ],
      "related_categories": [],
      "content_length": 963,
      "confidence_score": 0.13333333333333333
    },
    {
      "id": "46203b3b3284",
      "title": "入院予定の父が「大部屋はゆっくり眠れない」と“個室”を希望！「どうせ高額療養費で戻ってくる」とのことですが、差額ベッド代も対象ですか？ 1日“8000円”かかるので心配です……病気などの診療で高額な費用がかかった場合、健康保険に加入していれば「高額療養費制度」を利用でき、診療にかかった一部の費用が払い戻されます。しかし、診…ファイナンシャルフィールドライフ総合1/31(土) 13:50",
      "url": "https://news.yahoo.co.jp/articles/60025e59b715ff65693565b5614466facd6c274a",
      "source": "Yahoo!ニュース",
      "category": "健康保険",
      "summary": "【健康保険】 入院予定の父が「大部屋はゆっくり眠れない」と“個室”を希望！... (8000円, 5年7月) [令和5年]",
      "importance": "低",
      "published_date": null,
      "scraped_at": "2026-01-31T19:16:21.667273",
      "keywords": [
        "8000円",
        "厚生労働省",
        "5年7月",
        "8437円"
      ],
      "related_categories": [],
      "content_length": 1254,
      "confidence_score": 0.26666666666666666
    },
    {
      "id": "378862948d37",
      "title": "＜1分で解説＞コールセンターでAIが音声案内 SBI新生銀が導入…Q AIはどんなふうに答えてくれるの？ A 記者が「健康保険証があれば口座開設はできますか？」と聞くと、AIは「いいえ。健康保険証ではできません。本人確認には、マイナ…毎日新聞経済総合1/31(土) 13:29",
      "url": "https://news.yahoo.co.jp/articles/2e00e948a78ee29dffb31852edd41e2b76bbf15e",
      "source": "Yahoo!ニュース",
      "category": "健康保険",
      "summary": "【健康保険】 ＜1分で解説＞コールセンターでAIが音声案内 SBI新生銀が... [2月2日]",
      "importance": "低",
      "published_date": null,
      "scraped_at": "2026-01-31T19:16:22.987464",
      "keywords": [],
      "related_categories": [],
      "content_length": 611,
      "confidence_score": 0.5333333333333333
    },
    {
      "id": "e996d24b0521",
      "title": "【世帯主が65歳以上】「働くシニアも含めた二人以上世帯」平均貯蓄額はいくら？《無職・二人以上世帯》の平均貯蓄額の推移も見てみる…。 この背景には、食料品や光熱費などの物価上昇が続いていることに加え、介護保険料や後期高齢者医療保険料の引き上げ、さらには高額療養費制度の見直しなど、…LIMO経済総合1/31(土) 13:05",
      "url": "https://news.yahoo.co.jp/articles/829751b50c584e511d56aa3a6acd8fceaef6d19e",
      "source": "Yahoo!ニュース",
      "category": "健康保険",
      "summary": "【健康保険】 【世帯主が65歳以上】「働くシニアも含めた二人以上世帯」平均... (3万円, 2818円, 6521円) [令和6年]",
      "importance": "中",
      "published_date": null,
      "scraped_at": "2026-01-31T19:16:44.757325",
      "keywords": [
        "3万円",
        "2818円",
        "6521円",
        "356円",
        "1080万円"
      ],
      "related_categories": [
        "介護保険",
        "社会保険全般"
      ],
      "content_length": 1064,
      "confidence_score": 0.13333333333333333
    }
  ]
}