{
  "category": "介護保険",
  "count": 9,
  "news": [
    {
      "id": "85c092e284ec",
      "title": "仕事を減らして“母の介護”をしたいのですが、会社に時短勤務制度がありません……。“収入減”を補う「公的制度」はありますか？…とで収入が減る場合、雇用保険の制度として「介護休業給付金」を受給できます。以下、詳しく確認していきます。 1.支給要件 雇用保険の被保険者であること。ファイナンシャルフィールド経済総合10/21(火) 7:40",
      "url": "https://news.yahoo.co.jp/articles/05608032656ae2fc18c45998081c5e495dee89fa",
      "source": "Yahoo!ニュース",
      "category": "介護保険",
      "summary": "【介護保険】 仕事を減らして“母の介護”をしたいのですが、会社に時短勤務制...",
      "importance": "低",
      "published_date": null,
      "scraped_at": "2025-10-24T19:11:28.957827",
      "keywords": [],
      "related_categories": [
        "雇用保険",
        "社会保険全般"
      ],
      "content_length": 1021,
      "confidence_score": 0.7
    },
    {
      "id": "969ade8bc6ad",
      "title": "「帰ってきてよ」要介護3の妻を“自宅介護”に戻した75歳夫が、半年後に泣いたワケ…在宅介護を支える制度として、「訪問介護」「訪問看護」「デイサービス」などの介護保険サービスが整備されていますが、利用回数や時間には制限があり、家族による「…THE GOLD ONLINE（ゴールドオンライン）ライフ総合10/24(金) 16:00",
      "url": "https://news.yahoo.co.jp/articles/c0ef3f24aeffc6608355555ec303150c13810b36",
      "source": "Yahoo!ニュース",
      "category": "介護保険",
      "summary": "【介護保険】 「帰ってきてよ」要介護3の妻を“自宅介護”に戻した75歳夫が...",
      "importance": "低",
      "published_date": null,
      "scraped_at": "2025-10-24T19:11:39.367342",
      "keywords": [],
      "related_categories": [],
      "content_length": 948,
      "confidence_score": 0.5333333333333333
    },
    {
      "id": "1e31641a41a9",
      "title": "認知症の母の排泄問題に不安を感じた息子がケアマネに相談した訪問介護のこと「新たに見直をしたケアプランの中身」…60分の利用」といったように、介護保険サービスを利用する人の心身状態、本人や家族の希望などを加味しながら、様々な介護保険サービスの種類や頻度を決めた計…介護ポストセブンライフ総合10/24(金) 7:15",
      "url": "https://news.yahoo.co.jp/articles/2d1536aa1812b6a5efd39563f52858bae207a3f4",
      "source": "Yahoo!ニュース",
      "category": "介護保険",
      "summary": "【介護保険】 認知症の母の排泄問題に不安を感じた息子がケアマネに相談した訪... [12月13日]",
      "importance": "中",
      "published_date": null,
      "scraped_at": "2025-10-24T19:11:40.650098",
      "keywords": [],
      "related_categories": [],
      "content_length": 1222,
      "confidence_score": 1.0
    },
    {
      "id": "fb6a28160357",
      "title": "「仕事は辞めない」母の遺言と介護 ジェーン・スー語る…た母が倒れ、どちらも入院していたので介護のために半年間、休職しました。介護保険や保険外サービスなどの知識が私にはなかったため、親戚の力を借りながらやれ…朝日新聞科学10/23(木) 15:00",
      "url": "https://news.yahoo.co.jp/articles/8ec8c51615b904b56319e7fd0b3819f6fd7cf629",
      "source": "Yahoo!ニュース",
      "category": "介護保険",
      "summary": "【介護保険】 「仕事は辞めない」母の遺言と介護 ジェーン・スー語る…た母が... (2025年10月) [2025年10月]",
      "importance": "中",
      "published_date": null,
      "scraped_at": "2025-10-24T19:11:41.972844",
      "keywords": [
        "2025年10月"
      ],
      "related_categories": [],
      "content_length": 2356,
      "confidence_score": 0.5333333333333333
    },
    {
      "id": "719e9c759ce4",
      "title": "【介護用おむつに関する意識調査】家族＆ケアマネの本音とは？「介護家族の6割超が夜間交換が負担」「ケアマネが勧める際のポイントは吸収力」…※1 厚生労働省「令和7年5月分 介護保険事業状況報告（暫定）結果の概要－p.1」および「第9期計画期間における介護保険の第1号保険料について集計結果－p…介護ポストセブンライフ総合10/23(木) 11:15",
      "url": "https://news.yahoo.co.jp/articles/608a61c7e1521d2adc97ffd13669376b33b171cb",
      "source": "Yahoo!ニュース",
      "category": "介護保険",
      "summary": "【介護保険】 【介護用おむつに関する意識調査】家族＆ケアマネの本音とは？「... (7年5月, 2025年5月) [2025年5月]",
      "importance": "中",
      "published_date": null,
      "scraped_at": "2025-10-24T19:11:43.259646",
      "keywords": [
        "厚生労働省",
        "7年5月",
        "2025年5月"
      ],
      "related_categories": [],
      "content_length": 888,
      "confidence_score": 0.7333333333333333
    },
    {
      "id": "7340b32bb66d",
      "title": "＜紀北町長選＞候補者の横顔…ある」との持論を展開。弱者への「愛情表現」とし、福祉タクシーの無料化や介護保険料免除を訴える。現町政については「なぜ特別養護老人ホームを建て替えないのか」と批判する。伊勢新聞三重10/23(木) 8:00",
      "url": "https://news.yahoo.co.jp/articles/5d255b04fe802443766e35ac57c3360fa706de53",
      "source": "Yahoo!ニュース",
      "category": "介護保険",
      "summary": "【介護保険】 ＜紀北町長選＞候補者の横顔…ある」との持論を展開。弱者への「...",
      "importance": "高",
      "published_date": null,
      "scraped_at": "2025-10-24T19:11:44.678098",
      "keywords": [
        "健康保険組合"
      ],
      "related_categories": [
        "健康保険"
      ],
      "content_length": 1554,
      "confidence_score": 0.26666666666666666
    },
    {
      "id": "7ebfd3aef485",
      "title": "神戸市長選挙に立候補した4氏の経歴・政策まとめ…○賃上げ・女性雇用・正規化支援 ○高校卒業まで教育費・医療費は完全無料に ○国保料・介護保険料の1万円引き下げ ・賃上げ支援金10万円、女性雇用・正規化支援金10万…選挙ドットコム政治10/23(木) 7:13",
      "url": "https://news.yahoo.co.jp/articles/2eaa74885d5c1d83d7b8b533512ba3f9de7d32cd",
      "source": "Yahoo!ニュース",
      "category": "介護保険",
      "summary": "【介護保険】 神戸市長選挙に立候補した4氏の経歴・政策まとめ…○賃上げ・女... (10万円, 1万円) [10月12日]",
      "importance": "高",
      "published_date": null,
      "scraped_at": "2025-10-24T19:11:46.014890",
      "keywords": [
        "10万円",
        "1万円"
      ],
      "related_categories": [],
      "content_length": 4788,
      "confidence_score": 0.13333333333333333
    },
    {
      "id": "e3f140f149f8",
      "title": "助けてくれ！〈手取り月19万円〉35歳非正規男性、68歳父が脳梗塞。自己負担1割で〈介護費用・月12万円〉の悪夢…私たちは何を理解しておくべきでしょうか。 まず、介護費用の要となるのが介護保険制度です。65歳以上の場合、本人の合計所得金額が160万円未満であれば1…THE GOLD ONLINE（ゴールドオンライン）ライフ総合10/23(木) 5:00",
      "url": "https://news.yahoo.co.jp/articles/d3af6d675769b1cfd1cfc2a930d5a98c6bbd4d54",
      "source": "Yahoo!ニュース",
      "category": "介護保険",
      "summary": "【介護保険】 助けてくれ！〈手取り月19万円〉35歳非正規男性、68歳父が... (19万円, 12万円, 160万円)",
      "importance": "低",
      "published_date": null,
      "scraped_at": "2025-10-24T19:11:47.368213",
      "keywords": [
        "19万円",
        "12万円",
        "160万円"
      ],
      "related_categories": [],
      "content_length": 1144,
      "confidence_score": 0.2333333333333333
    },
    {
      "id": "54b16b94c6a9",
      "title": "入浴介助中に90代の入所者が「60度」の湯に 1カ月半後に死亡…果関係を調べるとともに、業務上過失致死容疑を視野に捜査している。 市介護保険課によると、施設側は市の調査に「湯は60度ぐらいで、職員が温度確認を怠っ…朝日新聞社会10/22(水) 11:30",
      "url": "https://news.yahoo.co.jp/articles/baa99a364a25ffedddde21bff2fef4a9b1f30f21",
      "source": "Yahoo!ニュース",
      "category": "介護保険",
      "summary": "【介護保険】 入浴介助中に90代の入所者が「60度」の湯に 1カ月半後に死... [8月4日]",
      "importance": "低",
      "published_date": null,
      "scraped_at": "2025-10-24T19:11:50.193072",
      "keywords": [],
      "related_categories": [],
      "content_length": 651,
      "confidence_score": 0.26666666666666666
    }
  ]
}