{
  "date": "2025年09月08日",
  "summary": {
    "total_news": 53,
    "high_importance": 8,
    "categories": [
      "その他",
      "介護保険",
      "社会保険全般",
      "厚生年金",
      "雇用保険",
      "労災保険",
      "健康保険"
    ],
    "top_keywords": [
      "厚生労働省",
      "800万円",
      "2025年9月",
      "1000万円",
      "500万円",
      "７年１月",
      "2000万円",
      "3000円",
      "000万円",
      "5000円"
    ]
  },
  "highlights": [
    {
      "id": "540e6a6c7cef",
      "title": "厚生年金保険の保険給付及び保険料の納付の特例等に関する法律の施行状況に関する報告（第34回）",
      "url": "https://www.mhlw.go.jp/stf/houdou/newpage_00187.html",
      "source": "厚生労働省",
      "category": "厚生年金",
      "summary": "【厚生年金】 厚生年金保険の保険給付及び保険料の納付の特例等に関する法律の...",
      "importance": "高",
      "published_date": "2025年1月28日",
      "scraped_at": "2025-09-08T19:09:56.370682",
      "keywords": [],
      "related_categories": [],
      "content_length": 0,
      "confidence_score": 0.13333333333333333
    },
    {
      "id": "a0a2d417e133",
      "title": "3:49「急な話で私たちも驚いている」石破総理退陣へ自民党長崎県連からは驚きの声…いかなと僕は思います。給料の問題とかもあるので、手取りの部分を増やし、社会保険料少し安くしていただければなという現役世代の声です」 女性「次はどなたになるんですかね…NBC長崎放送長崎9/8(月) 18:42",
      "url": "https://news.yahoo.co.jp/articles/7b900544d0208b0b18f39be357982ca883314369",
      "source": "Yahoo!ニュース",
      "category": "社会保険全般",
      "summary": "【社会保険全般】 3:49「急な話で私たちも驚いている」石破総理退陣へ自民党長...",
      "importance": "高",
      "published_date": null,
      "scraped_at": "2025-09-08T19:10:10.325581",
      "keywords": [],
      "related_categories": [],
      "content_length": 862,
      "confidence_score": 0.26666666666666666
    },
    {
      "id": "1dd8bcc0c861",
      "title": "石破総理の辞任の真意とポスト石破の行方は 自民党内の思惑について専門家が解説…』といわれています。維新が掲げている政策、『副首都構想』『憲法改正』『社会保険料の引き下げ』いずれも自民党にとってハードルは高くありません。維新との政…テレビ愛知愛知9/8(月) 18:25",
      "url": "https://news.yahoo.co.jp/articles/5fd4c197249d41bc7ef17ef744cf3c73b3d910a6",
      "source": "Yahoo!ニュース",
      "category": "社会保険全般",
      "summary": "【社会保険全般】 石破総理の辞任の真意とポスト石破の行方は 自民党内の思惑につ...",
      "importance": "高",
      "published_date": null,
      "scraped_at": "2025-09-08T19:10:13.034965",
      "keywords": [],
      "related_categories": [],
      "content_length": 865,
      "confidence_score": 0.4666666666666666
    },
    {
      "id": "d0206d1d687c",
      "title": "石破総理が辞任表明 次期総裁に求める条件は2つ？選挙ドットコム編集長が分析「高市氏でもなく小泉氏でもない第三者に行く可能性がある」…の副首都構想なので、これを間違いなく連立の条件にしてくるであろう。次は社会保険料の引き下げ、それから憲法改正も視野に入ってくるかもしれない」 また、…ABEMA TIMES政治9/8(月) 16:30",
      "url": "https://news.yahoo.co.jp/articles/f840a7580848872a15dd4d33027a3d8b325732ff",
      "source": "Yahoo!ニュース",
      "category": "社会保険全般",
      "summary": "【社会保険全般】 石破総理が辞任表明 次期総裁に求める条件は2つ？選挙ドットコ... [9月7日]",
      "importance": "高",
      "published_date": null,
      "scraped_at": "2025-09-08T19:10:14.384160",
      "keywords": [],
      "related_categories": [],
      "content_length": 898,
      "confidence_score": 0.4666666666666666
    },
    {
      "id": "1281de0c7f73",
      "title": "【後期高齢者医療制度】「2割負担」の配慮措置が9月末で終了！2026年度からは子ども・子育て支援金の徴収がスタート…しかし、政府によると、この保険料の増加分は「歳出改革」と「賃上げ」による実質的な社会保険負担軽減効果の範囲内で導入することとされています。 まとめにかえて本記…LIMO経済総合9/8(月) 14:16",
      "url": "https://news.yahoo.co.jp/articles/75648b12aeb8125ce0524589175d316237cd95e3",
      "source": "Yahoo!ニュース",
      "category": "社会保険全般",
      "summary": "【社会保険全般】 【後期高齢者医療制度】「2割負担」の配慮措置が9月末で終了！... (320万円, 200万円, 28万円) [2025年9月]",
      "importance": "高",
      "published_date": null,
      "scraped_at": "2025-09-08T19:10:19.711850",
      "keywords": [
        "320万円",
        "200万円",
        "28万円",
        "2022年10月",
        "2025年9月",
        "3000円"
      ],
      "related_categories": [
        "健康保険"
      ],
      "content_length": 1184,
      "confidence_score": 0.8666666666666666
    }
  ]
}