{
  "last_updated": "2025-07-30T19:33:52.811156",
  "total_count": 51,
  "categories": {
    "厚生年金": [
      {
        "id": "41181c1bde5c",
        "title": "国民年金保険料の月次納付率について（令和６年11月末現在）",
        "url": "https://www.mhlw.go.jp/stf/houdou/newpage_00189.html",
        "source": "厚生労働省",
        "category": "厚生年金",
        "summary": "【厚生年金】 国民年金保険料の月次納付率について（令和６年11月末現在）... (６年11月)",
        "importance": "低",
        "published_date": "2025年1月31日",
        "scraped_at": "2025-07-30T19:32:21.988141",
        "keywords": [
          "６年11月"
        ],
        "related_categories": [],
        "content_length": 0,
        "confidence_score": 0.16666666666666669
      },
      {
        "id": "540e6a6c7cef",
        "title": "厚生年金保険の保険給付及び保険料の納付の特例等に関する法律の施行状況に関する報告（第34回）",
        "url": "https://www.mhlw.go.jp/stf/houdou/newpage_00187.html",
        "source": "厚生労働省",
        "category": "厚生年金",
        "summary": "【厚生年金】 厚生年金保険の保険給付及び保険料の納付の特例等に関する法律の...",
        "importance": "高",
        "published_date": "2025年1月28日",
        "scraped_at": "2025-07-30T19:32:23.225550",
        "keywords": [],
        "related_categories": [],
        "content_length": 0,
        "confidence_score": 0.13333333333333333
      },
      {
        "id": "9f30d58374ae",
        "title": "令和７年度における国民年金保険料の前納額について",
        "url": "https://www.mhlw.go.jp/stf/houdou/0000190457_00018.html",
        "source": "厚生労働省",
        "category": "厚生年金",
        "summary": "【厚生年金】 令和７年度における国民年金保険料の前納額",
        "importance": "低",
        "published_date": "2025年1月24日",
        "scraped_at": "2025-07-30T19:32:24.469841",
        "keywords": [],
        "related_categories": [],
        "content_length": 0,
        "confidence_score": 0.16666666666666669
      },
      {
        "id": "1aeb558bf4c0",
        "title": "国民年金保険料の月次納付率について（令和６年10月末現在）",
        "url": "https://www.mhlw.go.jp/stf/houdou/newpage_00185.html",
        "source": "厚生労働省",
        "category": "厚生年金",
        "summary": "【厚生年金】 国民年金保険料の月次納付率について（令和６年10月末現在）... (６年10月)",
        "importance": "低",
        "published_date": "2024年12月20日",
        "scraped_at": "2025-07-30T19:32:27.185155",
        "keywords": [
          "６年10月"
        ],
        "related_categories": [],
        "content_length": 0,
        "confidence_score": 0.16666666666666669
      },
      {
        "id": "be4b39831788",
        "title": "72歳で年金が「月7万円」しかなく、家賃や食費も払うのがやっとです。受けられる支援はあるでしょうか？ すぐにできることはありますか？…内 執筆者 : 辻章嗣 ウィングFP相談室 代表 CFP(R)認定者、社会保険労務士…ファイナンシャルフィールド経済総合7/30(水) 18:40",
        "url": "https://news.yahoo.co.jp/articles/01938d3eab1da67958f09d4ffab552b49115bfb2",
        "source": "Yahoo!ニュース",
        "category": "厚生年金",
        "summary": "【厚生年金】 72歳で年金が「月7万円」しかなく、家賃や食費も払うのがやっ... (5450円, 5000円) [令和7年]",
        "importance": "中",
        "published_date": null,
        "scraped_at": "2025-07-30T19:32:38.417400",
        "keywords": [
          "5450円",
          "5000円",
          "厚生労働省",
          "10万円",
          "7万円",
          "1551円",
          "社会保険労務士"
        ],
        "related_categories": [
          "社会保険全般"
        ],
        "content_length": 1025,
        "confidence_score": 1.0
      },
      {
        "id": "d5e36b583cc8",
        "title": "【老後資金2000万円以上】貯めている世帯は何パーセント？夫婦で年金「月額15万円」あれば生活できるのか？ ・直接税 1万1162円 ・社会保険料 1万9171円 ・合計 28万6877円 ※諸雑費以下はその他の主な消費支出の内訳 社会保険料と税金をあわせた平均…LIMO経済総合7/30(水) 15:16",
        "url": "https://news.yahoo.co.jp/articles/bf3c0d1cc25f1e1b7265ac49ae444872c782a001",
        "source": "Yahoo!ニュース",
        "category": "厚生年金",
        "summary": "【厚生年金】 【老後資金2000万円以上】貯めている世帯は何パーセント？夫... (6877円, 15万円) [令和6年]",
        "importance": "低",
        "published_date": null,
        "scraped_at": "2025-07-30T19:32:41.155840",
        "keywords": [
          "厚生労働省",
          "6877円",
          "15万円",
          "9171円",
          "2000万円",
          "1162円"
        ],
        "related_categories": [
          "社会保険全般"
        ],
        "content_length": 1629,
        "confidence_score": 1.0
      },
      {
        "id": "3e2dd2137b8a",
        "title": "【平均年金月額】都道府県別の1位「厚生年金は神奈川県」「国民年金は富山県」将来の受給額を増やす方法はあるか…75万円以上の方の場合、10年間、保険料（本人負担分）が月9100円（社会保険料控除の考慮で月約6100円）増えることになりますが、老後に月約5100…LIMO経済総合7/30(水) 15:11",
        "url": "https://news.yahoo.co.jp/articles/35734ab58f556c0b03359756ebde889d1c953230",
        "source": "Yahoo!ニュース",
        "category": "厚生年金",
        "summary": "【厚生年金】 【平均年金月額】都道府県別の1位「厚生年金は神奈川県」「国民... (65万円, 6100円) [6月13日]",
        "importance": "高",
        "published_date": null,
        "scraped_at": "2025-07-30T19:32:42.540679",
        "keywords": [
          "65万円",
          "6100円",
          "厚生労働省",
          "75万円",
          "9100円"
        ],
        "related_categories": [
          "社会保険全般"
        ],
        "content_length": 1047,
        "confidence_score": 1.0
      },
      {
        "id": "160186442b4d",
        "title": "年金「月15万円」を受給していた68歳の夫が死亡。ずっと専業主婦だった「67歳の妻」は、遺族年金を“いつから・いくら”受け取れる？ 遺族が「未支給年金」も受給できるケースも解説…日本年金機構 遺族年金ガイド 令和7年度版 執筆者 : 橋本典子 特定社会保険労務士・FP1級技能士…ファイナンシャルフィールド経済総合7/30(水) 13:30",
        "url": "https://news.yahoo.co.jp/articles/75124ccec17cd05aab9d2602850761e26973dc1c",
        "source": "Yahoo!ニュース",
        "category": "厚生年金",
        "summary": "【厚生年金】 年金「月15万円」を受給していた68歳の夫が死亡。ずっと専業... (15万円, 7500円) [3月31日]",
        "importance": "低",
        "published_date": null,
        "scraped_at": "2025-07-30T19:32:43.918812",
        "keywords": [
          "社会保険労務士",
          "15万円",
          "7500円",
          "年金機構"
        ],
        "related_categories": [
          "社会保険全般"
        ],
        "content_length": 1802,
        "confidence_score": 1.0
      },
      {
        "id": "b70117596256",
        "title": "【夏のボーナス】平均はいくら？日本の平均年収とともに解説！将来に向けたお金の準備3つ…●iDeCoは自分でつくる年金制度 iDeCo（個人型確定拠出年金）は、老後の生活資金を自分で準備する制度です。 毎月積み立てたお金を、60歳以降に年金または一時金…LIMO経済総合7/30(水) 19:31",
        "url": "https://news.yahoo.co.jp/articles/578cd4b0f4a0233023313ba1e0363ece6055a66e",
        "source": "Yahoo!ニュース",
        "category": "厚生年金",
        "summary": "【厚生年金】 【夏のボーナス】平均はいくら？日本の平均年収とともに解説！将... (7000円, 80万円, 2025年6月) [2025年6月]",
        "importance": "低",
        "published_date": null,
        "scraped_at": "2025-07-30T19:32:54.853136",
        "keywords": [
          "7000円",
          "80万円",
          "2025年6月",
          "8000円",
          "100円",
          "100万円",
          "2024年9月",
          "461万円"
        ],
        "related_categories": [
          "健康保険",
          "雇用保険",
          "介護保険"
        ],
        "content_length": 1374,
        "confidence_score": 0.3
      },
      {
        "id": "9bf2f2af534d",
        "title": "コロナワクチン接種の死亡事例含む12件を認定 - 厚労省の予防接種審査分科会…」が34件（認定11件）、「障害年金」が4件（認定なし）、「死亡一時金・葬祭料」が3件（認定1件）、「障害児養育年金」が1件（認定なし）だった。 今…医療介護ＣＢニュース社会7/30(水) 17:00",
        "url": "https://news.yahoo.co.jp/articles/8035f58597d6dbae8b95da79cc4ea67fc7056bf1",
        "source": "Yahoo!ニュース",
        "category": "厚生年金",
        "summary": "【厚生年金】 コロナワクチン接種の死亡事例含む12件を認定 - 厚労省の予...",
        "importance": "低",
        "published_date": null,
        "scraped_at": "2025-07-30T19:33:03.274325",
        "keywords": [
          "厚生労働省"
        ],
        "related_categories": [],
        "content_length": 261,
        "confidence_score": 0.26666666666666666
      },
      {
        "id": "a157458d34b5",
        "title": "「雇用調整助成金」の不正受給ワーストは愛知県 6月末で累計1,764件 業種別の最多は飲食業…は1,026件で約6割（構成比58.1％）を占めた。パートタイマー等の雇用保険被保険者でない従業員の休業に支給される「緊急雇用安定助成金」のみは236件（同13…東京商工リサーチ経済総合7/30(水) 13:34",
        "url": "https://news.yahoo.co.jp/articles/8d969377d11059d8f026b23df123dca977ddba2f",
        "source": "Yahoo!ニュース",
        "category": "厚生年金",
        "summary": "【厚生年金】 「雇用調整助成金」の不正受給ワーストは愛知県 6月末で累計1... (82万円, 2024年10月, 2025年6月) [2025年6月]",
        "importance": "低",
        "published_date": null,
        "scraped_at": "2025-07-30T19:33:22.152911",
        "keywords": [
          "82万円",
          "2024年10月",
          "2025年6月",
          "2020年4月"
        ],
        "related_categories": [
          "雇用保険",
          "社会保険全般"
        ],
        "content_length": 847,
        "confidence_score": 0.8
      },
      {
        "id": "c2459686b232",
        "title": "繰上げ受給後に再就職して厚生年金加入「掛けた分が全然増えません」62歳女性の困惑…かなか見つからず、見つかったのは社会保険（厚生年金保険・健康保険）にも雇用保険にも入れない短時間勤務の仕事ばかりでした。これで少しは収入が得られるよう…Finasee経済総合7/29(火) 16:47",
        "url": "https://news.yahoo.co.jp/articles/f0b530c46fd7610705af503b04f5e3921969eecf",
        "source": "Yahoo!ニュース",
        "category": "厚生年金",
        "summary": "【厚生年金】 繰上げ受給後に再就職して厚生年金加入「掛けた分が全然増えませ... (年金事務所)",
        "importance": "低",
        "published_date": null,
        "scraped_at": "2025-07-30T19:33:27.749775",
        "keywords": [
          "年金事務所"
        ],
        "related_categories": [
          "健康保険",
          "雇用保険",
          "社会保険全般"
        ],
        "content_length": 1402,
        "confidence_score": 1.0
      }
    ],
    "その他": [
      {
        "id": "2255eafb1ceb",
        "title": "令和７年度の年金額改定について",
        "url": "https://www.mhlw.go.jp/stf/houdou/0000191631_00019.html",
        "source": "厚生労働省",
        "category": "その他",
        "summary": "【その他】 令和７年度の年金額改定 (2025年1月, ７年１月) [2025年1月]",
        "importance": "中",
        "published_date": "2025年１月24日",
        "scraped_at": "2025-07-30T19:32:25.688346",
        "keywords": [
          "2025年1月",
          "７年１月",
          "厚生労働省"
        ],
        "related_categories": [],
        "content_length": 433,
        "confidence_score": 0.0
      },
      {
        "id": "c5c5e93dbba7",
        "title": "令和６年能登半島地震関係 石川県の一部地域における労働保険料、障害者雇用納付金などの、申告・納期限の延長後の期限を令和７年１月31日と決定しました",
        "url": "https://www.mhlw.go.jp/stf/newpage_46733.html",
        "source": "厚生労働省",
        "category": "その他",
        "summary": "【その他】 令和６年能登半島地震関係 石川県の一部地域における労働保険料... (７年１月)",
        "importance": "低",
        "published_date": "2025年１月31日",
        "scraped_at": "2025-07-30T19:32:29.644308",
        "keywords": [
          "７年１月"
        ],
        "related_categories": [],
        "content_length": 0,
        "confidence_score": 0.0
      },
      {
        "id": "53a15300c2b7",
        "title": "「日本人ファースト」にかき消されたロスジェネ対策……雨宮処凛「参院選は最後の希望だった」…ネの中には、ずっと非正規雇用で働いてきて、私含め国民年金にしか加入していない、あるいはその国民年金の保険料さえ払うことができない人たちがたくさんいます…みんかぶマガジン経済総合7/30(水) 19:10",
        "url": "https://news.yahoo.co.jp/articles/452c60da90c1b966151e5263ee6a59723bbf1c4f",
        "source": "Yahoo!ニュース",
        "category": "その他",
        "summary": "【その他】 「日本人ファースト」にかき消されたロスジェネ対策……雨宮処凛...",
        "importance": "中",
        "published_date": null,
        "scraped_at": "2025-07-30T19:32:56.202390",
        "keywords": [],
        "related_categories": [],
        "content_length": 943,
        "confidence_score": 0.0
      },
      {
        "id": "073862330675",
        "title": "「年金の払戻金がある」「今すぐATMへ」年金事務所職員かたる男らから電話 60代女性が現金およそ100万円の被害 山梨…年金事務所の職員や銀行員を名乗る男からの電話で「年金の見直しで払戻金がある」「今すぐATMへ行ってください」などというウソの話を信じた60代の女性が…UTYテレビ山梨山梨7/30(水) 17:45",
        "url": "https://news.yahoo.co.jp/articles/ce5249a5f3297f2e406117e1e79953b4b0f85236",
        "source": "Yahoo!ニュース",
        "category": "その他",
        "summary": "【その他】 「年金の払戻金がある」「今すぐATMへ」年金事務所職員かたる... (年金事務所, 100万円, 7318円)",
        "importance": "中",
        "published_date": null,
        "scraped_at": "2025-07-30T19:32:57.660234",
        "keywords": [
          "年金事務所",
          "100万円",
          "7318円"
        ],
        "related_categories": [],
        "content_length": 677,
        "confidence_score": 0.0
      },
      {
        "id": "400ae20b0b3c",
        "title": "民間なのに「公務員」扱い！みなし公務員は「通常の公務員」と収入はどのくらい違うの？…「郵便法」第74条により、公務に従事する職員とみなされます。 ・日本年金機構の役員と職員 「日本年金機構法」第20条により、公務に従事する職員とみなされます。 …ファイナンシャルフィールド経済総合7/30(水) 17:40",
        "url": "https://news.yahoo.co.jp/articles/d6e20e7fbc9f22e9c7830dfcb53e86cc10b87812",
        "source": "Yahoo!ニュース",
        "category": "その他",
        "summary": "【その他】 民間なのに「公務員」扱い！みなし公務員は「通常の公務員」と収... (年金機構)",
        "importance": "低",
        "published_date": null,
        "scraped_at": "2025-07-30T19:32:59.050304",
        "keywords": [
          "年金機構"
        ],
        "related_categories": [],
        "content_length": 886,
        "confidence_score": 0.0
      },
      {
        "id": "66ed085aa18f",
        "title": "松山千春 玉木雄一郎氏に超大物を“紹介”した過去 「あの玉木がここまで…」国民民主の躍進に感慨…も選挙戦を見ていて、最初は物価高を何とかしてくれとか社会保障問題、医療や年金、介護、少子化、高齢化社会に対する不安とかな、そういう問題があったんだけど…スポニチアネックスエンタメ総合7/30(水) 17:33",
        "url": "https://news.yahoo.co.jp/articles/39ddcf6c4ffb014303e89b03fda07017c64f48f3",
        "source": "Yahoo!ニュース",
        "category": "その他",
        "summary": "【その他】 松山千春 玉木雄一郎氏に超大物を“紹介”した過去 「あの玉木...",
        "importance": "低",
        "published_date": null,
        "scraped_at": "2025-07-30T19:33:00.416512",
        "keywords": [],
        "related_categories": [],
        "content_length": 910,
        "confidence_score": 0.0
      },
      {
        "id": "d275ac329473",
        "title": "外国人の子ども支援に取り組む小原ブラスさん：「言葉を学ぶ大切さは公園で教えてもらった」…それは経済的に必要だからです。日本も人口減の時代に、外国人が働き、税金を納め、年金などの制度を支えてくれている面がある。もう「共に生きていくしかない」時代に…nippon.com社会7/30(水) 17:00",
        "url": "https://news.yahoo.co.jp/articles/8b0923e0ed474ee698410d0e73cf93605884647d",
        "source": "Yahoo!ニュース",
        "category": "その他",
        "summary": "【その他】 外国人の子ども支援に取り組む小原ブラスさん：「言葉を学ぶ大切...",
        "importance": "低",
        "published_date": null,
        "scraped_at": "2025-07-30T19:33:01.862252",
        "keywords": [],
        "related_categories": [],
        "content_length": 971,
        "confidence_score": 0.0
      },
      {
        "id": "c62bb9d8c9e6",
        "title": "「高市首相」になっても何も変わらないのに…裏金議員が「石破やめろ」と攻め立てる\"自民党の厚顔体質\"…ない政治が8カ月以上続くことになった。 物価高対策や少子高齢化を控えた年金改革、消費税の減税問題、全て先送りにされてきた。内閣不信任案を提出すれば可…プレジデントオンライン政治7/30(水) 16:16",
        "url": "https://news.yahoo.co.jp/articles/3d5d81314084385d2589f2e6c48f7de487e8c197",
        "source": "Yahoo!ニュース",
        "category": "その他",
        "summary": "【その他】 「高市首相」になっても何も変わらないのに…裏金議員が「石破や... (2025年7月) [2025年7月]",
        "importance": "低",
        "published_date": null,
        "scraped_at": "2025-07-30T19:33:04.548974",
        "keywords": [
          "2025年7月"
        ],
        "related_categories": [],
        "content_length": 1425,
        "confidence_score": 0.0
      }
    ],
    "労災保険": [
      {
        "id": "5fe3382dd6ed",
        "title": "「令和５年度 石綿による疾病に関する労災保険給付などの請求・決定状況まとめ（確定値）」を公表します",
        "url": "https://www.mhlw.go.jp/stf/newpage_46437.html",
        "source": "厚生労働省",
        "category": "労災保険",
        "summary": "【労災保険】 「令和５年度 石綿による疾病に関する労災保険給付などの請求・...",
        "importance": "低",
        "published_date": "2024年12月11日",
        "scraped_at": "2025-07-30T19:32:28.414428",
        "keywords": [],
        "related_categories": [],
        "content_length": 0,
        "confidence_score": 0.13333333333333333
      }
    ],
    "社会保険全般": [
      {
        "id": "64db381e11de",
        "title": "ハラスメントを恐れる「就職氷河期世代」と対面での会話が苦手な「若手世代」が知らないと損すること…わればすぐに帰宅する人が増えているに違いない。 さらに物価上昇や増税、社会保険料の負担増大、上がらない給料などの問題もあって、若手世代を中心に節約志向…All Aboutライフ総合7/30(水) 21:35",
        "url": "https://news.yahoo.co.jp/articles/8e584c19ab51c4336b5310a40dfaaed1463279f8",
        "source": "Yahoo!ニュース",
        "category": "社会保険全般",
        "summary": "【社会保険全般】 ハラスメントを恐れる「就職氷河期世代」と対面での会話が苦手な...",
        "importance": "低",
        "published_date": null,
        "scraped_at": "2025-07-30T19:32:37.063848",
        "keywords": [],
        "related_categories": [],
        "content_length": 1374,
        "confidence_score": 0.26666666666666666
      },
      {
        "id": "c53c53eee691",
        "title": "日本の部長、平均給与「62万7,200円」だが…まもなく迎える「厳しい定年後」…部長の平均賃金「62万7,200円」というと一見高額ですが、これは税金や社会保険料を控除する前の額面であり、手取りでは50万円程度となります。 この中か…THE GOLD ONLINE（ゴールドオンライン）経済総合7/30(水) 16:09",
        "url": "https://news.yahoo.co.jp/articles/108c1b787a83d1d83896fda94e351c1433e54f35",
        "source": "Yahoo!ニュース",
        "category": "社会保険全般",
        "summary": "【社会保険全般】 日本の部長、平均給与「62万7,200円」だが…まもなく迎え... (200円, 50万円) [令和6年]",
        "importance": "低",
        "published_date": null,
        "scraped_at": "2025-07-30T19:32:39.783307",
        "keywords": [
          "200円",
          "50万円",
          "厚生労働省"
        ],
        "related_categories": [],
        "content_length": 1015,
        "confidence_score": 0.26666666666666666
      },
      {
        "id": "2b92d0316246",
        "title": "維新・吉村氏の連立否定は「現時点」の条件付き 政界流動化で悲願の副首都実現に虎視眈々…は考えていません」 吉村氏は29日の記者会見でこう述べ、参院選で掲げた社会保険料引き下げや大阪・関西を拠点とする「副首都構想」など公約の実現を目指す考…産経新聞政治7/30(水) 12:08",
        "url": "https://news.yahoo.co.jp/articles/1884a461d489def3d1add9e6c324c689e1633827",
        "source": "Yahoo!ニュース",
        "category": "社会保険全般",
        "summary": "【社会保険全般】 維新・吉村氏の連立否定は「現時点」の条件付き 政界流動化で悲... [令和4年]",
        "importance": "低",
        "published_date": null,
        "scraped_at": "2025-07-30T19:32:45.412183",
        "keywords": [],
        "related_categories": [],
        "content_length": 967,
        "confidence_score": 0.26666666666666666
      },
      {
        "id": "ee07591d5fb4",
        "title": "「それ、パワハラですよ！」部下からの“逆ハラ”指摘に上司は戦々恐々… 指導との境界線は？社労士が解説…このような状況で適切な指導をおこなうためには、上司はどうすればいいのだろうか。社会保険労務士法人こころ社労士事務所の香川昌彦さんに聞いた。 ー指導とパワハラの…よろず～ニュースライフ総合7/30(水) 11:50",
        "url": "https://news.yahoo.co.jp/articles/9cfa9a659267f5ad187975f569806bafdeaef399",
        "source": "Yahoo!ニュース",
        "category": "社会保険全般",
        "summary": "【社会保険全般】 「それ、パワハラですよ！」部下からの“逆ハラ”指摘に上司は戦...",
        "importance": "低",
        "published_date": null,
        "scraped_at": "2025-07-30T19:32:46.807391",
        "keywords": [
          "社会保険労務士"
        ],
        "related_categories": [],
        "content_length": 1345,
        "confidence_score": 0.4
      },
      {
        "id": "c67f8b31dff3",
        "title": "「挟まれた世代」60代男性が危機に直面…韓国社会の見落とされた層…先進国中で最悪レベルだ。欧米諸国では引退後の幸福度が高まるが、韓国では社会保険の恩恵を受けられず、むしろ幸福度は低下する。政府の年金制度導入は歴史的に…KOREA WAVE韓国・北朝鮮7/30(水) 11:03",
        "url": "https://news.yahoo.co.jp/articles/ad9a4929773de8b99152badf1438b6275ac6b4c6",
        "source": "Yahoo!ニュース",
        "category": "社会保険全般",
        "summary": "【社会保険全般】 「挟まれた世代」60代男性が危機に直面…韓国社会の見落とされ... (2025年6月) [07月30日]",
        "importance": "低",
        "published_date": null,
        "scraped_at": "2025-07-30T19:32:48.207412",
        "keywords": [
          "2025年6月"
        ],
        "related_categories": [],
        "content_length": 1255,
        "confidence_score": 0.26666666666666666
      },
      {
        "id": "76a8acb0132c",
        "title": "地方の中小企業勤務の男性では結婚できない…この10年間で起きた「結婚可能年収のインフレ」という大問題…面の年収があがったからといって、手取りが増えていないのが今の問題です。社会保険料負担は増え続けている上に、さらに「子育て支援金」などという新たな負担が…プレジデントオンライン社会7/30(水) 9:17",
        "url": "https://news.yahoo.co.jp/articles/548b53f9f0ebc89b9ad38c5a0f8af5e61721d03a",
        "source": "Yahoo!ニュース",
        "category": "社会保険全般",
        "summary": "【社会保険全般】 地方の中小企業勤務の男性では結婚できない…この10年間で起き... (300万円, 700万円)",
        "importance": "低",
        "published_date": null,
        "scraped_at": "2025-07-30T19:32:49.571416",
        "keywords": [
          "300万円",
          "700万円"
        ],
        "related_categories": [],
        "content_length": 1130,
        "confidence_score": 0.13333333333333333
      },
      {
        "id": "5657fd9e3b28",
        "title": "「家庭に入って家事や育児を頑張りたかった」本音にヒット…参政党の求心力の背景にある「女性の潜在的ニーズ」…されるようになり、しかもやたら長生きなので男性以上にたっぷり社会保険や介護保険を享受してあの世に逝くもんだから、世間からの風当たりはじわじわと強まっていく。プレジデントオンライン政治7/29(火) 18:17",
        "url": "https://news.yahoo.co.jp/articles/40a81177c6499243411cd4d9c7434c9d1e97ca17",
        "source": "Yahoo!ニュース",
        "category": "社会保険全般",
        "summary": "【社会保険全般】 「家庭に入って家事や育児を頑張りたかった」本音にヒット…参政... (2025年7月) [2025年7月]",
        "importance": "低",
        "published_date": null,
        "scraped_at": "2025-07-30T19:33:44.085835",
        "keywords": [
          "2025年7月"
        ],
        "related_categories": [
          "介護保険"
        ],
        "content_length": 1011,
        "confidence_score": 0.26666666666666666
      }
    ],
    "健康保険": [
      {
        "id": "158b29ae9e60",
        "title": "「LINE交換しませんか？」“億ション”に住む女性客が“借金漬け”のウーバー配達員に友達申請→価値観がズレまくる「異世界交流」が…え、うそ？まさか最後に泣かされるとは…と全力で警戒した。 けれど当時、僕から奪える金融資産はゼロだった。国民年金は滞納。健康保険は未加入。住民税は猶予。国の社会福祉課から20万円、父親か…ダイヤモンド・オンライン社会7/30(水) 21:01",
        "url": "https://news.yahoo.co.jp/articles/d4bb9755a63de436568c56562a52eaecb39d683b",
        "source": "Yahoo!ニュース",
        "category": "健康保険",
        "summary": "【健康保険】 「LINE交換しませんか？」“億ション”に住む女性客が“借金... (30万円, 20万円, 6000円)",
        "importance": "低",
        "published_date": null,
        "scraped_at": "2025-07-30T19:32:53.432191",
        "keywords": [
          "30万円",
          "20万円",
          "6000円"
        ],
        "related_categories": [],
        "content_length": 1487,
        "confidence_score": 0.26666666666666666
      },
      {
        "id": "fb0c973d4a3a",
        "title": "1:32後期高齢者など”紙の保険証” 有効期限31日まで 自治体が対応に追われる【佐賀県】…各市町の健康保険に加入する人などが持つ、いわゆる“紙の保険証”が31日で有効期限を迎える中、県内の自治体も対応に追われています。 “マイナ保険証”へ…佐賀ニュース サガテレビ佐賀7/30(水) 19:22",
        "url": "https://news.yahoo.co.jp/articles/bd96ae62265b9f5884be67ef9f8f586c134d9bc5",
        "source": "Yahoo!ニュース",
        "category": "健康保険",
        "summary": "【健康保険】 1:32後期高齢者など”紙の保険証” 有効期限31日まで 自...",
        "importance": "低",
        "published_date": null,
        "scraped_at": "2025-07-30T19:33:08.563542",
        "keywords": [],
        "related_categories": [],
        "content_length": 488,
        "confidence_score": 0.4
      },
      {
        "id": "fc453446726c",
        "title": "2:43紙の健康保険証が使えなくなる！国民健康保険・後期高齢者は７月末まで マイナ保険証か資格確認書で受診を…マイナンバーカードと一体化した「マイナ保険証」への移行に伴い、国民健康保険と後期高齢者医療制度の健康保険証が今月末で有効期限を迎えます。 何がどう変わるのか「ツイセキ」します。テレビ新広島広島7/30(水) 19:04",
        "url": "https://news.yahoo.co.jp/articles/398905fd259ec1aa83f2eb4624d12751db92863c",
        "source": "Yahoo!ニュース",
        "category": "健康保険",
        "summary": "【健康保険】 2:43紙の健康保険証が使えなくなる！国民健康保険・後期高齢... [７月３１日]",
        "importance": "低",
        "published_date": null,
        "scraped_at": "2025-07-30T19:33:09.986861",
        "keywords": [],
        "related_categories": [],
        "content_length": 1084,
        "confidence_score": 1.0
      },
      {
        "id": "df25adcbabaa",
        "title": "【福岡市】天神西通りにOPENのグラニフ福岡天神・原宿に次ぐカフェ併設店へ。男女で楽しめる雑貨や洋服…閉店情報を2件まとめてお知らせします（号外NET）【福岡市南区】「国民健康保険証」有効期限のご確認を。福岡県も注意喚起しています。マイナンバーカードを…いもひこ福岡7/30(水) 17:30",
        "url": "https://news.yahoo.co.jp/expert/articles/0aa81a72bf36e364663aeafdffae461391c12e61",
        "source": "Yahoo!ニュース",
        "category": "健康保険",
        "summary": "【健康保険】 【福岡市】天神西通りにOPENのグラニフ福岡天神・原宿に次ぐ...",
        "importance": "低",
        "published_date": null,
        "scraped_at": "2025-07-30T19:33:11.448123",
        "keywords": [],
        "related_categories": [],
        "content_length": 0,
        "confidence_score": 0.13333333333333333
      },
      {
        "id": "47fb509588bb",
        "title": "韓国の期待寿命８３．５歳…ＯＥＣＤ平均より２．４年長い…ＰＰ）基準で４５８６ドル（約６８万円）水準だ。 医療費全体のうち政府と健康保険など公的支出の割合は２０１３年の５５．９％から２０２３年には６０．４％に…中央日報日本語版韓国・北朝鮮7/30(水) 17:20",
        "url": "https://news.yahoo.co.jp/articles/223e6ed80ec1bf3622682aede553ce0f6b16440d",
        "source": "Yahoo!ニュース",
        "category": "健康保険",
        "summary": "【健康保険】 韓国の期待寿命８３．５歳…ＯＥＣＤ平均より２．４年長い…ＰＰ... (６８万円)",
        "importance": "低",
        "published_date": null,
        "scraped_at": "2025-07-30T19:33:12.865247",
        "keywords": [
          "６８万円"
        ],
        "related_categories": [],
        "content_length": 935,
        "confidence_score": 0.26666666666666666
      },
      {
        "id": "9380f3448c96",
        "title": "「レベル低すぎる」参政党・梅村みずほ氏 政策議論の「朝生」で繰り返したマウンティングの「2文字」に疑問続出…受給率）は3割という話もあったが、3パーセントに満たない。外国人が国民健康保険を悪用していると。国保に入っている人はいますけど、（加入率の割に）医療を…女性自身社会7/30(水) 16:33",
        "url": "https://news.yahoo.co.jp/articles/83e264107ecf4cae8686170c1f636a0aa6da9835",
        "source": "Yahoo!ニュース",
        "category": "健康保険",
        "summary": "【健康保険】 「レベル低すぎる」参政党・梅村みずほ氏 政策議論の「朝生」で... (19年7月) [6月30日]",
        "importance": "低",
        "published_date": null,
        "scraped_at": "2025-07-30T19:33:14.138224",
        "keywords": [
          "19年7月"
        ],
        "related_categories": [
          "厚生年金"
        ],
        "content_length": 2260,
        "confidence_score": 0.26666666666666666
      },
      {
        "id": "dfb1af43874c",
        "title": "母が「2人部屋」に2週間入院して、差額ベッド代が「5万円以上」…！個室だけが対象じゃないの？…者自身が追加で支払う費用です。正式には「特別療養環境室料」といいます。健康保険は適用されないため、全額自費負担が必要です。 対象となる部屋にはいくつか…ファイナンシャルフィールド経済総合7/30(水) 14:20",
        "url": "https://news.yahoo.co.jp/articles/353d27dcf469220a686206ec845d310563f000f2",
        "source": "Yahoo!ニュース",
        "category": "健康保険",
        "summary": "【健康保険】 母が「2人部屋」に2週間入院して、差額ベッド代が「5万円以上... (5万円, 1000万円)",
        "importance": "低",
        "published_date": null,
        "scraped_at": "2025-07-30T19:33:15.502219",
        "keywords": [
          "5万円",
          "1000万円"
        ],
        "related_categories": [],
        "content_length": 1023,
        "confidence_score": 0.26666666666666666
      },
      {
        "id": "37744c53e806",
        "title": "来年から徴収がスタートする予定の「子ども・子育て支援金」。独身で「年収600万円」の私は毎月いくら徴収されるのでしょうか？…：450円 ※全制度（被用者保険・協会けんぽ・健保組合・共済組合・国民健康保険・後期高齢者医療制度）の平均値 また、こども家庭庁の試算によると、被保険…ファイナンシャルフィールド経済総合7/30(水) 13:30",
        "url": "https://news.yahoo.co.jp/articles/06b600f18f5b7e18f6629dd04e4829bcce1ab34d",
        "source": "Yahoo!ニュース",
        "category": "健康保険",
        "summary": "【健康保険】 来年から徴収がスタートする予定の「子ども・子育て支援金」。独... (1000円, 6年6月, 600万円) [令和8年]",
        "importance": "低",
        "published_date": null,
        "scraped_at": "2025-07-30T19:33:16.880611",
        "keywords": [
          "1000円",
          "6年6月",
          "600万円",
          "250円",
          "協会けんぽ",
          "1000万円",
          "5年12月",
          "450円"
        ],
        "related_categories": [
          "社会保険全般"
        ],
        "content_length": 1335,
        "confidence_score": 1.0
      },
      {
        "id": "cccaf1ce0bdb",
        "title": "「会社が払ってくれる」は本当か 年収400万円の人が背負う38％の実質負担の正体…大きく「保険料方式」と「税方式」がある。日本では、健康保険・厚生年金・雇用保険・労災保険・介護保険などの社会保険が主に保険料方式で運営されており、その…遠藤司経済総合7/28(月) 7:30",
        "url": "https://news.yahoo.co.jp/expert/articles/ad813b42a46a9ad31aaa90748ba983600baceea6",
        "source": "Yahoo!ニュース",
        "category": "健康保険",
        "summary": "【健康保険】 「会社が払ってくれる」は本当か 年収400万円の人が背負う3... (400万円)",
        "importance": "低",
        "published_date": null,
        "scraped_at": "2025-07-30T19:33:30.551426",
        "keywords": [
          "400万円"
        ],
        "related_categories": [
          "厚生年金",
          "雇用保険",
          "労災保険",
          "介護保険",
          "社会保険全般"
        ],
        "content_length": 0,
        "confidence_score": 0.13333333333333333
      },
      {
        "id": "8be44d6d3a4d",
        "title": "通帳をみて心臓が止まるかと思った…「年金月28万円・貯金3,500万円」だったのに、定年9年後に夫急逝（享年69）→妻が「遺された50万円」で通夜も告別式もナシ“寂しすぎる葬式”を挙げざるを得なかったワケ…病は精神的にも経済的にも大きな負担となるため、妻名義の医療保険や民間の介護保険、そして十分な貯蓄を用意しておくことが、未来の安心に繋がるだろう。 この…THE GOLD ONLINE（ゴールドオンライン）経済総合7/30(水) 9:32",
        "url": "https://news.yahoo.co.jp/articles/bb51459004e40a7985e605a31c15ddbeabc41882",
        "source": "Yahoo!ニュース",
        "category": "健康保険",
        "summary": "【健康保険】 通帳をみて心臓が止まるかと思った…「年金月28万円・貯金3,... (50万円, 28万円, 500万円) [令和5年]",
        "importance": "低",
        "published_date": null,
        "scraped_at": "2025-07-30T19:33:39.854935",
        "keywords": [
          "50万円",
          "28万円",
          "500万円",
          "厚生労働省"
        ],
        "related_categories": [
          "厚生年金",
          "介護保険"
        ],
        "content_length": 1357,
        "confidence_score": 0.13333333333333333
      },
      {
        "id": "3ab020c908d4",
        "title": "【75歳からの医療費】2割負担になる人の年金収入はどれくらい？《後期高齢者医療制度》判定基準を解説…外来医療費の負担が実質的に増加する可能性があります。 加えて、物価高や介護保険料の引き上げといった社会的な変化も重なり、高齢者世帯の家計はますます厳しさを増しています。LIMO経済総合7/29(火) 18:13",
        "url": "https://news.yahoo.co.jp/articles/cec61ccc580b42a594e3e24b3b18a9bddd1835dc",
        "source": "Yahoo!ニュース",
        "category": "健康保険",
        "summary": "【健康保険】 【75歳からの医療費】2割負担になる人の年金収入はどれくらい... (2025年10月, 3000円, 2025年9月) [2025年10月]",
        "importance": "中",
        "published_date": null,
        "scraped_at": "2025-07-30T19:33:45.429681",
        "keywords": [
          "2025年10月",
          "3000円",
          "2025年9月",
          "2022年10月",
          "協会けんぽ"
        ],
        "related_categories": [
          "介護保険",
          "社会保険全般"
        ],
        "content_length": 1181,
        "confidence_score": 0.5666666666666667
      }
    ],
    "雇用保険": [
      {
        "id": "0030dc627786",
        "title": "2025年4月から育休給付が100％にアップすると聞きましたが、条件があると聞きました。満額で受け取るにはどうすればいいですか？…、なぜ“手取りで100％”という表現になるのでしょうか？ 育児休業中は健康保険料・厚生年金保険料が免除され、さらに勤務先から給与が支給されない場合には…ファイナンシャルフィールド経済総合7/30(水) 11:41",
        "url": "https://news.yahoo.co.jp/articles/be0d0f9c578bd221d914ae6a488361f8e551a2b8",
        "source": "Yahoo!ニュース",
        "category": "雇用保険",
        "summary": "【雇用保険】 2025年4月から育休給付が100％にアップすると聞きました... (3万円, 2023年12月, 5690円) [2025年4月]",
        "importance": "中",
        "published_date": null,
        "scraped_at": "2025-07-30T19:33:18.257375",
        "keywords": [
          "3万円",
          "2023年12月",
          "5690円",
          "2025年4月",
          "67%"
        ],
        "related_categories": [
          "健康保険",
          "厚生年金",
          "社会保険全般"
        ],
        "content_length": 1162,
        "confidence_score": 1.0
      },
      {
        "id": "8eb6c02775c0",
        "title": "【65歳以上の受講者6割以上が就職】無料で学べて手当ももらえる？「公共職業訓練と求職者支援訓練」とは？…。 公共職業訓練（離職者訓練）とは？雇用保険受給者向けの無料訓練制度公共職業訓練（離職者訓練）は、主に雇用保険を受給している、または受給資格のある離…LIMO経済総合7/30(水) 12:06",
        "url": "https://news.yahoo.co.jp/articles/1b68462b4705f1d0f4b105d20cffb4219403b64e",
        "source": "Yahoo!ニュース",
        "category": "雇用保険",
        "summary": "【雇用保険】 【65歳以上の受講者6割以上が就職】無料で学べて手当ももらえ... (500円) [令和5年]",
        "importance": "低",
        "published_date": null,
        "scraped_at": "2025-07-30T19:33:23.488393",
        "keywords": [
          "500円",
          "厚生労働省"
        ],
        "related_categories": [
          "厚生年金"
        ],
        "content_length": 1305,
        "confidence_score": 0.5333333333333333
      },
      {
        "id": "5d0125972d68",
        "title": "「育休取得者の36％が男性」過去最高に…韓国・中小企業勤務は今も“遠慮ムード”…政統計」によると、今年1月から6月までに育児休業給付金を初めて受給した雇用保険加入者は9万5064人で、前年同期（6万9631人）から37.4％増加した。KOREA WAVE韓国・北朝鮮7/30(水) 10:06",
        "url": "https://news.yahoo.co.jp/articles/57294b7de46588b0d5541c1e0c1f5840cad24c44",
        "source": "Yahoo!ニュース",
        "category": "雇用保険",
        "summary": "【雇用保険】 「育休取得者の36％が男性」過去最高に…韓国・中小企業勤務は... (34万円) [07月30日]",
        "importance": "高",
        "published_date": null,
        "scraped_at": "2025-07-30T19:33:24.945415",
        "keywords": [
          "34万円"
        ],
        "related_categories": [
          "厚生年金"
        ],
        "content_length": 978,
        "confidence_score": 0.6666666666666666
      },
      {
        "id": "d85aa6783ce2",
        "title": "女性にわいせつ行為、ハローワークで…職員の男逮捕、体を触った疑い 数年前から面識あった2人、個室で相談中に襲いかかる「抱き付いたけど、触ってない」…その後、理由不明の不起訴に 同署によると、6月18日に女性の親族から「春日部市内のハローワークに雇用保険の手続きで通所していたところ、体を触られた」と署に相談があった。男と女性…埼玉新聞埼玉7/30(水) 6:13",
        "url": "https://news.yahoo.co.jp/articles/7f21de35af5f5c3d8497c66ab5baaccd6d74c793",
        "source": "Yahoo!ニュース",
        "category": "雇用保険",
        "summary": "【雇用保険】 女性にわいせつ行為、ハローワークで…職員の男逮捕、体を触った... [5月22日]",
        "importance": "低",
        "published_date": null,
        "scraped_at": "2025-07-30T19:33:26.343190",
        "keywords": [],
        "related_categories": [],
        "content_length": 439,
        "confidence_score": 0.26666666666666666
      },
      {
        "id": "c3e73aff825e",
        "title": "50代からの親の介護で“やってはいけないこと”とは？FPが警鐘を鳴らすワケ…2人以上なら最大10日まで休暇を取ることが可能です。正社員だけでなく、雇用保険に加入して一定期間働いているパートやアルバイトの方も使えます。2025年…女子SPA！ライフ総合7/28(月) 8:46",
        "url": "https://news.yahoo.co.jp/articles/a8aad9d0696f59708c56936b37d7fabcdfae594e",
        "source": "Yahoo!ニュース",
        "category": "雇用保険",
        "summary": "【雇用保険】 50代からの親の介護で“やってはいけないこと”とは？FPが警... (2025年4月) [2025年4月]",
        "importance": "低",
        "published_date": null,
        "scraped_at": "2025-07-30T19:33:29.145035",
        "keywords": [
          "2025年4月"
        ],
        "related_categories": [
          "社会保険全般"
        ],
        "content_length": 1293,
        "confidence_score": 0.26666666666666666
      },
      {
        "id": "b76034668e9e",
        "title": "定年退職したら「失業保険」はもらえない？「65歳前」の退職で受給できるケースはありますか？…の退職で受け取れる可能性があるのは、失業保険と呼ばれる雇用保険の基本手当ではありません。雇用保険では、満65歳に達した日を境として保険者の区分が変わる…ファイナンシャルフィールドライフ総合7/27(日) 8:10",
        "url": "https://news.yahoo.co.jp/articles/04445d7d6e560f05c7d1f47b96d59807168218f1",
        "source": "Yahoo!ニュース",
        "category": "雇用保険",
        "summary": "【雇用保険】 定年退職したら「失業保険」はもらえない？「65歳前」の退職で... (8万円)",
        "importance": "低",
        "published_date": null,
        "scraped_at": "2025-07-30T19:33:31.901821",
        "keywords": [
          "8万円"
        ],
        "related_categories": [
          "厚生年金",
          "社会保険全般"
        ],
        "content_length": 1334,
        "confidence_score": 0.9333333333333332
      }
    ],
    "介護保険": [
      {
        "id": "9fe148e90b52",
        "title": "終の棲家にできる？値段や入るための条件や「こんなはずじゃなかった…」まで！安心して暮らせるシニアの住まい「サ高住」のリアル…なっています（外部と言っても、サ高住の約4分の3にはデイサービスなどの介護保険事業所や診療所が併設されています）。なお、重度の要介護者や認知症を発症し…webマガジン mi-molletライフ総合7/30(水) 20:33",
        "url": "https://news.yahoo.co.jp/articles/d7ab1477fa63d78022e65fca6f69cd01339a136b",
        "source": "Yahoo!ニュース",
        "category": "介護保険",
        "summary": "【介護保険】 終の棲家にできる？値段や入るための条件や「こんなはずじゃなか... (30万円, 2025年6月) [2025年6月]",
        "importance": "高",
        "published_date": null,
        "scraped_at": "2025-07-30T19:33:35.810684",
        "keywords": [
          "30万円",
          "2025年6月"
        ],
        "related_categories": [
          "社会保険全般"
        ],
        "content_length": 1585,
        "confidence_score": 0.7666666666666666
      },
      {
        "id": "a870cf48a562",
        "title": "【津波関連情報】「青森市役所」市役所駅前庁舎の1階で5つの課が一時窓口業務停止 駅ビル「ラビナ」では1階のテナントの従業員や利用客が2階以上に避難…青森市によりますと、午後0時15分現在、市役所駅前庁舎では1階にある市民課や介護保険課など5つの課が一時窓口業務を停止。職員や利用者が2階以上に避難したとい…ＡＴＶ青森テレビ青森7/30(水) 13:39",
        "url": "https://news.yahoo.co.jp/articles/1320196adbd62d324ce9799070edd29f425c036e",
        "source": "Yahoo!ニュース",
        "category": "介護保険",
        "summary": "【介護保険】 【津波関連情報】「青森市役所」市役所駅前庁舎の1階で5つの課...",
        "importance": "低",
        "published_date": null,
        "scraped_at": "2025-07-30T19:33:37.160463",
        "keywords": [],
        "related_categories": [],
        "content_length": 287,
        "confidence_score": 0.26666666666666666
      },
      {
        "id": "7d8f2ef46479",
        "title": "これを間違えると親子関係が悪化することが多い…FPは知っている「親の介護で絶対手を出してはいけないもの」…んが出しました。その後、介護認定を受けている人であれば改修費用の一部が介護保険から支給されることを知った穴水さん。しかし申請すると、自治体から、「改修…プレジデントオンライン経済総合7/30(水) 10:16",
        "url": "https://news.yahoo.co.jp/articles/56bfcd736176594367f571345fded1517901c8f9",
        "source": "Yahoo!ニュース",
        "category": "介護保険",
        "summary": "【介護保険】 これを間違えると親子関係が悪化することが多い…FPは知ってい... (10万円, 13万円, 5万円)",
        "importance": "中",
        "published_date": null,
        "scraped_at": "2025-07-30T19:33:38.503506",
        "keywords": [
          "10万円",
          "13万円",
          "5万円"
        ],
        "related_categories": [],
        "content_length": 1119,
        "confidence_score": 0.2333333333333333
      },
      {
        "id": "f528847f9264",
        "title": "【最新研究】要介護高齢者のQOL向上には「寒暖」より≪明るさ・におい≫対策がカギ！ 安価で始められる、理想の住宅環境づくりとは？…。 ■安価で始められる照明・におい対策、おすすめは 厚生労働省は、介護保険において要支援、要介護の認定を受けた人の一定の住宅改修に対し補助金を設け…東洋経済オンラインライフ総合7/30(水) 8:32",
        "url": "https://news.yahoo.co.jp/articles/634ab601444ec2850c828bb47a0f8fe9e429f579",
        "source": "Yahoo!ニュース",
        "category": "介護保険",
        "summary": "【介護保険】 【最新研究】要介護高齢者のQOL向上には「寒暖」より≪明るさ...",
        "importance": "低",
        "published_date": null,
        "scraped_at": "2025-07-30T19:33:41.315036",
        "keywords": [
          "厚生労働省"
        ],
        "related_categories": [],
        "content_length": 1070,
        "confidence_score": 0.9333333333333333
      },
      {
        "id": "8cfe91cb7b70",
        "title": "年１０万人の「介護離職」どう防ぐ…仕事と両立できる「環境づくり」実践へ国が企業向け指針…通じて企業に実践を促すことにした。 社員に「自分で介護をしすぎず、介護保険サービスを利用する」よう呼びかけることや、面談時のチェックシートを通じ介…読売新聞オンライン社会7/29(火) 19:32",
        "url": "https://news.yahoo.co.jp/articles/f5ba2b979b5946dc831e5ffeceff72d4bc561f38",
        "source": "Yahoo!ニュース",
        "category": "介護保険",
        "summary": "【介護保険】 年１０万人の「介護離職」どう防ぐ…仕事と両立できる「環境づく... (２２年１月, ２０２１年６月, ２２年９月) [２０２１年６月]",
        "importance": "中",
        "published_date": null,
        "scraped_at": "2025-07-30T19:33:42.685112",
        "keywords": [
          "２２年１月",
          "２０２１年６月",
          "２２年９月",
          "厚生労働省"
        ],
        "related_categories": [],
        "content_length": 854,
        "confidence_score": 0.13333333333333333
      },
      {
        "id": "ff624b7bb0ca",
        "title": "岡山で一人暮らしの母が要介護に…どうする？ 頼りは「チーム」 ケアマネを軸に見守り体制つくる…あって一人暮らしなら、なおさらです。住み慣れた自宅で生活を続けるには、介護保険サービスなどを活用した見守りの体制作りがカギを握ります。（野島正徳） …読売新聞（ヨミドクター）科学7/29(火) 18:04",
        "url": "https://news.yahoo.co.jp/articles/3e9be62927d0720056da83a31b55550399dd703f",
        "source": "Yahoo!ニュース",
        "category": "介護保険",
        "summary": "【介護保険】 岡山で一人暮らしの母が要介護に…どうする？ 頼りは「チーム」... [6月4日]",
        "importance": "低",
        "published_date": null,
        "scraped_at": "2025-07-30T19:33:46.802221",
        "keywords": [],
        "related_categories": [],
        "content_length": 1144,
        "confidence_score": 0.4666666666666666
      }
    ]
  },
  "importance_distribution": {
    "高": 4,
    "中": 8,
    "低": 39
  },
  "news": [
    {
      "id": "41181c1bde5c",
      "title": "国民年金保険料の月次納付率について（令和６年11月末現在）",
      "url": "https://www.mhlw.go.jp/stf/houdou/newpage_00189.html",
      "source": "厚生労働省",
      "category": "厚生年金",
      "summary": "【厚生年金】 国民年金保険料の月次納付率について（令和６年11月末現在）... (６年11月)",
      "importance": "低",
      "published_date": "2025年1月31日",
      "scraped_at": "2025-07-30T19:32:21.988141",
      "keywords": [
        "６年11月"
      ],
      "related_categories": [],
      "content_length": 0,
      "confidence_score": 0.16666666666666669
    },
    {
      "id": "540e6a6c7cef",
      "title": "厚生年金保険の保険給付及び保険料の納付の特例等に関する法律の施行状況に関する報告（第34回）",
      "url": "https://www.mhlw.go.jp/stf/houdou/newpage_00187.html",
      "source": "厚生労働省",
      "category": "厚生年金",
      "summary": "【厚生年金】 厚生年金保険の保険給付及び保険料の納付の特例等に関する法律の...",
      "importance": "高",
      "published_date": "2025年1月28日",
      "scraped_at": "2025-07-30T19:32:23.225550",
      "keywords": [],
      "related_categories": [],
      "content_length": 0,
      "confidence_score": 0.13333333333333333
    },
    {
      "id": "9f30d58374ae",
      "title": "令和７年度における国民年金保険料の前納額について",
      "url": "https://www.mhlw.go.jp/stf/houdou/0000190457_00018.html",
      "source": "厚生労働省",
      "category": "厚生年金",
      "summary": "【厚生年金】 令和７年度における国民年金保険料の前納額",
      "importance": "低",
      "published_date": "2025年1月24日",
      "scraped_at": "2025-07-30T19:32:24.469841",
      "keywords": [],
      "related_categories": [],
      "content_length": 0,
      "confidence_score": 0.16666666666666669
    },
    {
      "id": "2255eafb1ceb",
      "title": "令和７年度の年金額改定について",
      "url": "https://www.mhlw.go.jp/stf/houdou/0000191631_00019.html",
      "source": "厚生労働省",
      "category": "その他",
      "summary": "【その他】 令和７年度の年金額改定 (2025年1月, ７年１月) [2025年1月]",
      "importance": "中",
      "published_date": "2025年１月24日",
      "scraped_at": "2025-07-30T19:32:25.688346",
      "keywords": [
        "2025年1月",
        "７年１月",
        "厚生労働省"
      ],
      "related_categories": [],
      "content_length": 433,
      "confidence_score": 0.0
    },
    {
      "id": "1aeb558bf4c0",
      "title": "国民年金保険料の月次納付率について（令和６年10月末現在）",
      "url": "https://www.mhlw.go.jp/stf/houdou/newpage_00185.html",
      "source": "厚生労働省",
      "category": "厚生年金",
      "summary": "【厚生年金】 国民年金保険料の月次納付率について（令和６年10月末現在）... (６年10月)",
      "importance": "低",
      "published_date": "2024年12月20日",
      "scraped_at": "2025-07-30T19:32:27.185155",
      "keywords": [
        "６年10月"
      ],
      "related_categories": [],
      "content_length": 0,
      "confidence_score": 0.16666666666666669
    },
    {
      "id": "5fe3382dd6ed",
      "title": "「令和５年度 石綿による疾病に関する労災保険給付などの請求・決定状況まとめ（確定値）」を公表します",
      "url": "https://www.mhlw.go.jp/stf/newpage_46437.html",
      "source": "厚生労働省",
      "category": "労災保険",
      "summary": "【労災保険】 「令和５年度 石綿による疾病に関する労災保険給付などの請求・...",
      "importance": "低",
      "published_date": "2024年12月11日",
      "scraped_at": "2025-07-30T19:32:28.414428",
      "keywords": [],
      "related_categories": [],
      "content_length": 0,
      "confidence_score": 0.13333333333333333
    },
    {
      "id": "c5c5e93dbba7",
      "title": "令和６年能登半島地震関係 石川県の一部地域における労働保険料、障害者雇用納付金などの、申告・納期限の延長後の期限を令和７年１月31日と決定しました",
      "url": "https://www.mhlw.go.jp/stf/newpage_46733.html",
      "source": "厚生労働省",
      "category": "その他",
      "summary": "【その他】 令和６年能登半島地震関係 石川県の一部地域における労働保険料... (７年１月)",
      "importance": "低",
      "published_date": "2025年１月31日",
      "scraped_at": "2025-07-30T19:32:29.644308",
      "keywords": [
        "７年１月"
      ],
      "related_categories": [],
      "content_length": 0,
      "confidence_score": 0.0
    },
    {
      "id": "64db381e11de",
      "title": "ハラスメントを恐れる「就職氷河期世代」と対面での会話が苦手な「若手世代」が知らないと損すること…わればすぐに帰宅する人が増えているに違いない。 さらに物価上昇や増税、社会保険料の負担増大、上がらない給料などの問題もあって、若手世代を中心に節約志向…All Aboutライフ総合7/30(水) 21:35",
      "url": "https://news.yahoo.co.jp/articles/8e584c19ab51c4336b5310a40dfaaed1463279f8",
      "source": "Yahoo!ニュース",
      "category": "社会保険全般",
      "summary": "【社会保険全般】 ハラスメントを恐れる「就職氷河期世代」と対面での会話が苦手な...",
      "importance": "低",
      "published_date": null,
      "scraped_at": "2025-07-30T19:32:37.063848",
      "keywords": [],
      "related_categories": [],
      "content_length": 1374,
      "confidence_score": 0.26666666666666666
    },
    {
      "id": "be4b39831788",
      "title": "72歳で年金が「月7万円」しかなく、家賃や食費も払うのがやっとです。受けられる支援はあるでしょうか？ すぐにできることはありますか？…内 執筆者 : 辻章嗣 ウィングFP相談室 代表 CFP(R)認定者、社会保険労務士…ファイナンシャルフィールド経済総合7/30(水) 18:40",
      "url": "https://news.yahoo.co.jp/articles/01938d3eab1da67958f09d4ffab552b49115bfb2",
      "source": "Yahoo!ニュース",
      "category": "厚生年金",
      "summary": "【厚生年金】 72歳で年金が「月7万円」しかなく、家賃や食費も払うのがやっ... (5450円, 5000円) [令和7年]",
      "importance": "中",
      "published_date": null,
      "scraped_at": "2025-07-30T19:32:38.417400",
      "keywords": [
        "5450円",
        "5000円",
        "厚生労働省",
        "10万円",
        "7万円",
        "1551円",
        "社会保険労務士"
      ],
      "related_categories": [
        "社会保険全般"
      ],
      "content_length": 1025,
      "confidence_score": 1.0
    },
    {
      "id": "c53c53eee691",
      "title": "日本の部長、平均給与「62万7,200円」だが…まもなく迎える「厳しい定年後」…部長の平均賃金「62万7,200円」というと一見高額ですが、これは税金や社会保険料を控除する前の額面であり、手取りでは50万円程度となります。 この中か…THE GOLD ONLINE（ゴールドオンライン）経済総合7/30(水) 16:09",
      "url": "https://news.yahoo.co.jp/articles/108c1b787a83d1d83896fda94e351c1433e54f35",
      "source": "Yahoo!ニュース",
      "category": "社会保険全般",
      "summary": "【社会保険全般】 日本の部長、平均給与「62万7,200円」だが…まもなく迎え... (200円, 50万円) [令和6年]",
      "importance": "低",
      "published_date": null,
      "scraped_at": "2025-07-30T19:32:39.783307",
      "keywords": [
        "200円",
        "50万円",
        "厚生労働省"
      ],
      "related_categories": [],
      "content_length": 1015,
      "confidence_score": 0.26666666666666666
    },
    {
      "id": "d5e36b583cc8",
      "title": "【老後資金2000万円以上】貯めている世帯は何パーセント？夫婦で年金「月額15万円」あれば生活できるのか？ ・直接税 1万1162円 ・社会保険料 1万9171円 ・合計 28万6877円 ※諸雑費以下はその他の主な消費支出の内訳 社会保険料と税金をあわせた平均…LIMO経済総合7/30(水) 15:16",
      "url": "https://news.yahoo.co.jp/articles/bf3c0d1cc25f1e1b7265ac49ae444872c782a001",
      "source": "Yahoo!ニュース",
      "category": "厚生年金",
      "summary": "【厚生年金】 【老後資金2000万円以上】貯めている世帯は何パーセント？夫... (6877円, 15万円) [令和6年]",
      "importance": "低",
      "published_date": null,
      "scraped_at": "2025-07-30T19:32:41.155840",
      "keywords": [
        "厚生労働省",
        "6877円",
        "15万円",
        "9171円",
        "2000万円",
        "1162円"
      ],
      "related_categories": [
        "社会保険全般"
      ],
      "content_length": 1629,
      "confidence_score": 1.0
    },
    {
      "id": "3e2dd2137b8a",
      "title": "【平均年金月額】都道府県別の1位「厚生年金は神奈川県」「国民年金は富山県」将来の受給額を増やす方法はあるか…75万円以上の方の場合、10年間、保険料（本人負担分）が月9100円（社会保険料控除の考慮で月約6100円）増えることになりますが、老後に月約5100…LIMO経済総合7/30(水) 15:11",
      "url": "https://news.yahoo.co.jp/articles/35734ab58f556c0b03359756ebde889d1c953230",
      "source": "Yahoo!ニュース",
      "category": "厚生年金",
      "summary": "【厚生年金】 【平均年金月額】都道府県別の1位「厚生年金は神奈川県」「国民... (65万円, 6100円) [6月13日]",
      "importance": "高",
      "published_date": null,
      "scraped_at": "2025-07-30T19:32:42.540679",
      "keywords": [
        "65万円",
        "6100円",
        "厚生労働省",
        "75万円",
        "9100円"
      ],
      "related_categories": [
        "社会保険全般"
      ],
      "content_length": 1047,
      "confidence_score": 1.0
    },
    {
      "id": "160186442b4d",
      "title": "年金「月15万円」を受給していた68歳の夫が死亡。ずっと専業主婦だった「67歳の妻」は、遺族年金を“いつから・いくら”受け取れる？ 遺族が「未支給年金」も受給できるケースも解説…日本年金機構 遺族年金ガイド 令和7年度版 執筆者 : 橋本典子 特定社会保険労務士・FP1級技能士…ファイナンシャルフィールド経済総合7/30(水) 13:30",
      "url": "https://news.yahoo.co.jp/articles/75124ccec17cd05aab9d2602850761e26973dc1c",
      "source": "Yahoo!ニュース",
      "category": "厚生年金",
      "summary": "【厚生年金】 年金「月15万円」を受給していた68歳の夫が死亡。ずっと専業... (15万円, 7500円) [3月31日]",
      "importance": "低",
      "published_date": null,
      "scraped_at": "2025-07-30T19:32:43.918812",
      "keywords": [
        "社会保険労務士",
        "15万円",
        "7500円",
        "年金機構"
      ],
      "related_categories": [
        "社会保険全般"
      ],
      "content_length": 1802,
      "confidence_score": 1.0
    },
    {
      "id": "2b92d0316246",
      "title": "維新・吉村氏の連立否定は「現時点」の条件付き 政界流動化で悲願の副首都実現に虎視眈々…は考えていません」 吉村氏は29日の記者会見でこう述べ、参院選で掲げた社会保険料引き下げや大阪・関西を拠点とする「副首都構想」など公約の実現を目指す考…産経新聞政治7/30(水) 12:08",
      "url": "https://news.yahoo.co.jp/articles/1884a461d489def3d1add9e6c324c689e1633827",
      "source": "Yahoo!ニュース",
      "category": "社会保険全般",
      "summary": "【社会保険全般】 維新・吉村氏の連立否定は「現時点」の条件付き 政界流動化で悲... [令和4年]",
      "importance": "低",
      "published_date": null,
      "scraped_at": "2025-07-30T19:32:45.412183",
      "keywords": [],
      "related_categories": [],
      "content_length": 967,
      "confidence_score": 0.26666666666666666
    },
    {
      "id": "ee07591d5fb4",
      "title": "「それ、パワハラですよ！」部下からの“逆ハラ”指摘に上司は戦々恐々… 指導との境界線は？社労士が解説…このような状況で適切な指導をおこなうためには、上司はどうすればいいのだろうか。社会保険労務士法人こころ社労士事務所の香川昌彦さんに聞いた。 ー指導とパワハラの…よろず～ニュースライフ総合7/30(水) 11:50",
      "url": "https://news.yahoo.co.jp/articles/9cfa9a659267f5ad187975f569806bafdeaef399",
      "source": "Yahoo!ニュース",
      "category": "社会保険全般",
      "summary": "【社会保険全般】 「それ、パワハラですよ！」部下からの“逆ハラ”指摘に上司は戦...",
      "importance": "低",
      "published_date": null,
      "scraped_at": "2025-07-30T19:32:46.807391",
      "keywords": [
        "社会保険労務士"
      ],
      "related_categories": [],
      "content_length": 1345,
      "confidence_score": 0.4
    },
    {
      "id": "c67f8b31dff3",
      "title": "「挟まれた世代」60代男性が危機に直面…韓国社会の見落とされた層…先進国中で最悪レベルだ。欧米諸国では引退後の幸福度が高まるが、韓国では社会保険の恩恵を受けられず、むしろ幸福度は低下する。政府の年金制度導入は歴史的に…KOREA WAVE韓国・北朝鮮7/30(水) 11:03",
      "url": "https://news.yahoo.co.jp/articles/ad9a4929773de8b99152badf1438b6275ac6b4c6",
      "source": "Yahoo!ニュース",
      "category": "社会保険全般",
      "summary": "【社会保険全般】 「挟まれた世代」60代男性が危機に直面…韓国社会の見落とされ... (2025年6月) [07月30日]",
      "importance": "低",
      "published_date": null,
      "scraped_at": "2025-07-30T19:32:48.207412",
      "keywords": [
        "2025年6月"
      ],
      "related_categories": [],
      "content_length": 1255,
      "confidence_score": 0.26666666666666666
    },
    {
      "id": "76a8acb0132c",
      "title": "地方の中小企業勤務の男性では結婚できない…この10年間で起きた「結婚可能年収のインフレ」という大問題…面の年収があがったからといって、手取りが増えていないのが今の問題です。社会保険料負担は増え続けている上に、さらに「子育て支援金」などという新たな負担が…プレジデントオンライン社会7/30(水) 9:17",
      "url": "https://news.yahoo.co.jp/articles/548b53f9f0ebc89b9ad38c5a0f8af5e61721d03a",
      "source": "Yahoo!ニュース",
      "category": "社会保険全般",
      "summary": "【社会保険全般】 地方の中小企業勤務の男性では結婚できない…この10年間で起き... (300万円, 700万円)",
      "importance": "低",
      "published_date": null,
      "scraped_at": "2025-07-30T19:32:49.571416",
      "keywords": [
        "300万円",
        "700万円"
      ],
      "related_categories": [],
      "content_length": 1130,
      "confidence_score": 0.13333333333333333
    },
    {
      "id": "158b29ae9e60",
      "title": "「LINE交換しませんか？」“億ション”に住む女性客が“借金漬け”のウーバー配達員に友達申請→価値観がズレまくる「異世界交流」が…え、うそ？まさか最後に泣かされるとは…と全力で警戒した。 けれど当時、僕から奪える金融資産はゼロだった。国民年金は滞納。健康保険は未加入。住民税は猶予。国の社会福祉課から20万円、父親か…ダイヤモンド・オンライン社会7/30(水) 21:01",
      "url": "https://news.yahoo.co.jp/articles/d4bb9755a63de436568c56562a52eaecb39d683b",
      "source": "Yahoo!ニュース",
      "category": "健康保険",
      "summary": "【健康保険】 「LINE交換しませんか？」“億ション”に住む女性客が“借金... (30万円, 20万円, 6000円)",
      "importance": "低",
      "published_date": null,
      "scraped_at": "2025-07-30T19:32:53.432191",
      "keywords": [
        "30万円",
        "20万円",
        "6000円"
      ],
      "related_categories": [],
      "content_length": 1487,
      "confidence_score": 0.26666666666666666
    },
    {
      "id": "b70117596256",
      "title": "【夏のボーナス】平均はいくら？日本の平均年収とともに解説！将来に向けたお金の準備3つ…●iDeCoは自分でつくる年金制度 iDeCo（個人型確定拠出年金）は、老後の生活資金を自分で準備する制度です。 毎月積み立てたお金を、60歳以降に年金または一時金…LIMO経済総合7/30(水) 19:31",
      "url": "https://news.yahoo.co.jp/articles/578cd4b0f4a0233023313ba1e0363ece6055a66e",
      "source": "Yahoo!ニュース",
      "category": "厚生年金",
      "summary": "【厚生年金】 【夏のボーナス】平均はいくら？日本の平均年収とともに解説！将... (7000円, 80万円, 2025年6月) [2025年6月]",
      "importance": "低",
      "published_date": null,
      "scraped_at": "2025-07-30T19:32:54.853136",
      "keywords": [
        "7000円",
        "80万円",
        "2025年6月",
        "8000円",
        "100円",
        "100万円",
        "2024年9月",
        "461万円"
      ],
      "related_categories": [
        "健康保険",
        "雇用保険",
        "介護保険"
      ],
      "content_length": 1374,
      "confidence_score": 0.3
    },
    {
      "id": "53a15300c2b7",
      "title": "「日本人ファースト」にかき消されたロスジェネ対策……雨宮処凛「参院選は最後の希望だった」…ネの中には、ずっと非正規雇用で働いてきて、私含め国民年金にしか加入していない、あるいはその国民年金の保険料さえ払うことができない人たちがたくさんいます…みんかぶマガジン経済総合7/30(水) 19:10",
      "url": "https://news.yahoo.co.jp/articles/452c60da90c1b966151e5263ee6a59723bbf1c4f",
      "source": "Yahoo!ニュース",
      "category": "その他",
      "summary": "【その他】 「日本人ファースト」にかき消されたロスジェネ対策……雨宮処凛...",
      "importance": "中",
      "published_date": null,
      "scraped_at": "2025-07-30T19:32:56.202390",
      "keywords": [],
      "related_categories": [],
      "content_length": 943,
      "confidence_score": 0.0
    },
    {
      "id": "073862330675",
      "title": "「年金の払戻金がある」「今すぐATMへ」年金事務所職員かたる男らから電話 60代女性が現金およそ100万円の被害 山梨…年金事務所の職員や銀行員を名乗る男からの電話で「年金の見直しで払戻金がある」「今すぐATMへ行ってください」などというウソの話を信じた60代の女性が…UTYテレビ山梨山梨7/30(水) 17:45",
      "url": "https://news.yahoo.co.jp/articles/ce5249a5f3297f2e406117e1e79953b4b0f85236",
      "source": "Yahoo!ニュース",
      "category": "その他",
      "summary": "【その他】 「年金の払戻金がある」「今すぐATMへ」年金事務所職員かたる... (年金事務所, 100万円, 7318円)",
      "importance": "中",
      "published_date": null,
      "scraped_at": "2025-07-30T19:32:57.660234",
      "keywords": [
        "年金事務所",
        "100万円",
        "7318円"
      ],
      "related_categories": [],
      "content_length": 677,
      "confidence_score": 0.0
    },
    {
      "id": "400ae20b0b3c",
      "title": "民間なのに「公務員」扱い！みなし公務員は「通常の公務員」と収入はどのくらい違うの？…「郵便法」第74条により、公務に従事する職員とみなされます。 ・日本年金機構の役員と職員 「日本年金機構法」第20条により、公務に従事する職員とみなされます。 …ファイナンシャルフィールド経済総合7/30(水) 17:40",
      "url": "https://news.yahoo.co.jp/articles/d6e20e7fbc9f22e9c7830dfcb53e86cc10b87812",
      "source": "Yahoo!ニュース",
      "category": "その他",
      "summary": "【その他】 民間なのに「公務員」扱い！みなし公務員は「通常の公務員」と収... (年金機構)",
      "importance": "低",
      "published_date": null,
      "scraped_at": "2025-07-30T19:32:59.050304",
      "keywords": [
        "年金機構"
      ],
      "related_categories": [],
      "content_length": 886,
      "confidence_score": 0.0
    },
    {
      "id": "66ed085aa18f",
      "title": "松山千春 玉木雄一郎氏に超大物を“紹介”した過去 「あの玉木がここまで…」国民民主の躍進に感慨…も選挙戦を見ていて、最初は物価高を何とかしてくれとか社会保障問題、医療や年金、介護、少子化、高齢化社会に対する不安とかな、そういう問題があったんだけど…スポニチアネックスエンタメ総合7/30(水) 17:33",
      "url": "https://news.yahoo.co.jp/articles/39ddcf6c4ffb014303e89b03fda07017c64f48f3",
      "source": "Yahoo!ニュース",
      "category": "その他",
      "summary": "【その他】 松山千春 玉木雄一郎氏に超大物を“紹介”した過去 「あの玉木...",
      "importance": "低",
      "published_date": null,
      "scraped_at": "2025-07-30T19:33:00.416512",
      "keywords": [],
      "related_categories": [],
      "content_length": 910,
      "confidence_score": 0.0
    },
    {
      "id": "d275ac329473",
      "title": "外国人の子ども支援に取り組む小原ブラスさん：「言葉を学ぶ大切さは公園で教えてもらった」…それは経済的に必要だからです。日本も人口減の時代に、外国人が働き、税金を納め、年金などの制度を支えてくれている面がある。もう「共に生きていくしかない」時代に…nippon.com社会7/30(水) 17:00",
      "url": "https://news.yahoo.co.jp/articles/8b0923e0ed474ee698410d0e73cf93605884647d",
      "source": "Yahoo!ニュース",
      "category": "その他",
      "summary": "【その他】 外国人の子ども支援に取り組む小原ブラスさん：「言葉を学ぶ大切...",
      "importance": "低",
      "published_date": null,
      "scraped_at": "2025-07-30T19:33:01.862252",
      "keywords": [],
      "related_categories": [],
      "content_length": 971,
      "confidence_score": 0.0
    },
    {
      "id": "9bf2f2af534d",
      "title": "コロナワクチン接種の死亡事例含む12件を認定 - 厚労省の予防接種審査分科会…」が34件（認定11件）、「障害年金」が4件（認定なし）、「死亡一時金・葬祭料」が3件（認定1件）、「障害児養育年金」が1件（認定なし）だった。 今…医療介護ＣＢニュース社会7/30(水) 17:00",
      "url": "https://news.yahoo.co.jp/articles/8035f58597d6dbae8b95da79cc4ea67fc7056bf1",
      "source": "Yahoo!ニュース",
      "category": "厚生年金",
      "summary": "【厚生年金】 コロナワクチン接種の死亡事例含む12件を認定 - 厚労省の予...",
      "importance": "低",
      "published_date": null,
      "scraped_at": "2025-07-30T19:33:03.274325",
      "keywords": [
        "厚生労働省"
      ],
      "related_categories": [],
      "content_length": 261,
      "confidence_score": 0.26666666666666666
    },
    {
      "id": "c62bb9d8c9e6",
      "title": "「高市首相」になっても何も変わらないのに…裏金議員が「石破やめろ」と攻め立てる\"自民党の厚顔体質\"…ない政治が8カ月以上続くことになった。 物価高対策や少子高齢化を控えた年金改革、消費税の減税問題、全て先送りにされてきた。内閣不信任案を提出すれば可…プレジデントオンライン政治7/30(水) 16:16",
      "url": "https://news.yahoo.co.jp/articles/3d5d81314084385d2589f2e6c48f7de487e8c197",
      "source": "Yahoo!ニュース",
      "category": "その他",
      "summary": "【その他】 「高市首相」になっても何も変わらないのに…裏金議員が「石破や... (2025年7月) [2025年7月]",
      "importance": "低",
      "published_date": null,
      "scraped_at": "2025-07-30T19:33:04.548974",
      "keywords": [
        "2025年7月"
      ],
      "related_categories": [],
      "content_length": 1425,
      "confidence_score": 0.0
    },
    {
      "id": "fb0c973d4a3a",
      "title": "1:32後期高齢者など”紙の保険証” 有効期限31日まで 自治体が対応に追われる【佐賀県】…各市町の健康保険に加入する人などが持つ、いわゆる“紙の保険証”が31日で有効期限を迎える中、県内の自治体も対応に追われています。 “マイナ保険証”へ…佐賀ニュース サガテレビ佐賀7/30(水) 19:22",
      "url": "https://news.yahoo.co.jp/articles/bd96ae62265b9f5884be67ef9f8f586c134d9bc5",
      "source": "Yahoo!ニュース",
      "category": "健康保険",
      "summary": "【健康保険】 1:32後期高齢者など”紙の保険証” 有効期限31日まで 自...",
      "importance": "低",
      "published_date": null,
      "scraped_at": "2025-07-30T19:33:08.563542",
      "keywords": [],
      "related_categories": [],
      "content_length": 488,
      "confidence_score": 0.4
    },
    {
      "id": "fc453446726c",
      "title": "2:43紙の健康保険証が使えなくなる！国民健康保険・後期高齢者は７月末まで マイナ保険証か資格確認書で受診を…マイナンバーカードと一体化した「マイナ保険証」への移行に伴い、国民健康保険と後期高齢者医療制度の健康保険証が今月末で有効期限を迎えます。 何がどう変わるのか「ツイセキ」します。テレビ新広島広島7/30(水) 19:04",
      "url": "https://news.yahoo.co.jp/articles/398905fd259ec1aa83f2eb4624d12751db92863c",
      "source": "Yahoo!ニュース",
      "category": "健康保険",
      "summary": "【健康保険】 2:43紙の健康保険証が使えなくなる！国民健康保険・後期高齢... [７月３１日]",
      "importance": "低",
      "published_date": null,
      "scraped_at": "2025-07-30T19:33:09.986861",
      "keywords": [],
      "related_categories": [],
      "content_length": 1084,
      "confidence_score": 1.0
    },
    {
      "id": "df25adcbabaa",
      "title": "【福岡市】天神西通りにOPENのグラニフ福岡天神・原宿に次ぐカフェ併設店へ。男女で楽しめる雑貨や洋服…閉店情報を2件まとめてお知らせします（号外NET）【福岡市南区】「国民健康保険証」有効期限のご確認を。福岡県も注意喚起しています。マイナンバーカードを…いもひこ福岡7/30(水) 17:30",
      "url": "https://news.yahoo.co.jp/expert/articles/0aa81a72bf36e364663aeafdffae461391c12e61",
      "source": "Yahoo!ニュース",
      "category": "健康保険",
      "summary": "【健康保険】 【福岡市】天神西通りにOPENのグラニフ福岡天神・原宿に次ぐ...",
      "importance": "低",
      "published_date": null,
      "scraped_at": "2025-07-30T19:33:11.448123",
      "keywords": [],
      "related_categories": [],
      "content_length": 0,
      "confidence_score": 0.13333333333333333
    },
    {
      "id": "47fb509588bb",
      "title": "韓国の期待寿命８３．５歳…ＯＥＣＤ平均より２．４年長い…ＰＰ）基準で４５８６ドル（約６８万円）水準だ。 医療費全体のうち政府と健康保険など公的支出の割合は２０１３年の５５．９％から２０２３年には６０．４％に…中央日報日本語版韓国・北朝鮮7/30(水) 17:20",
      "url": "https://news.yahoo.co.jp/articles/223e6ed80ec1bf3622682aede553ce0f6b16440d",
      "source": "Yahoo!ニュース",
      "category": "健康保険",
      "summary": "【健康保険】 韓国の期待寿命８３．５歳…ＯＥＣＤ平均より２．４年長い…ＰＰ... (６８万円)",
      "importance": "低",
      "published_date": null,
      "scraped_at": "2025-07-30T19:33:12.865247",
      "keywords": [
        "６８万円"
      ],
      "related_categories": [],
      "content_length": 935,
      "confidence_score": 0.26666666666666666
    },
    {
      "id": "9380f3448c96",
      "title": "「レベル低すぎる」参政党・梅村みずほ氏 政策議論の「朝生」で繰り返したマウンティングの「2文字」に疑問続出…受給率）は3割という話もあったが、3パーセントに満たない。外国人が国民健康保険を悪用していると。国保に入っている人はいますけど、（加入率の割に）医療を…女性自身社会7/30(水) 16:33",
      "url": "https://news.yahoo.co.jp/articles/83e264107ecf4cae8686170c1f636a0aa6da9835",
      "source": "Yahoo!ニュース",
      "category": "健康保険",
      "summary": "【健康保険】 「レベル低すぎる」参政党・梅村みずほ氏 政策議論の「朝生」で... (19年7月) [6月30日]",
      "importance": "低",
      "published_date": null,
      "scraped_at": "2025-07-30T19:33:14.138224",
      "keywords": [
        "19年7月"
      ],
      "related_categories": [
        "厚生年金"
      ],
      "content_length": 2260,
      "confidence_score": 0.26666666666666666
    },
    {
      "id": "dfb1af43874c",
      "title": "母が「2人部屋」に2週間入院して、差額ベッド代が「5万円以上」…！個室だけが対象じゃないの？…者自身が追加で支払う費用です。正式には「特別療養環境室料」といいます。健康保険は適用されないため、全額自費負担が必要です。 対象となる部屋にはいくつか…ファイナンシャルフィールド経済総合7/30(水) 14:20",
      "url": "https://news.yahoo.co.jp/articles/353d27dcf469220a686206ec845d310563f000f2",
      "source": "Yahoo!ニュース",
      "category": "健康保険",
      "summary": "【健康保険】 母が「2人部屋」に2週間入院して、差額ベッド代が「5万円以上... (5万円, 1000万円)",
      "importance": "低",
      "published_date": null,
      "scraped_at": "2025-07-30T19:33:15.502219",
      "keywords": [
        "5万円",
        "1000万円"
      ],
      "related_categories": [],
      "content_length": 1023,
      "confidence_score": 0.26666666666666666
    },
    {
      "id": "37744c53e806",
      "title": "来年から徴収がスタートする予定の「子ども・子育て支援金」。独身で「年収600万円」の私は毎月いくら徴収されるのでしょうか？…：450円 ※全制度（被用者保険・協会けんぽ・健保組合・共済組合・国民健康保険・後期高齢者医療制度）の平均値 また、こども家庭庁の試算によると、被保険…ファイナンシャルフィールド経済総合7/30(水) 13:30",
      "url": "https://news.yahoo.co.jp/articles/06b600f18f5b7e18f6629dd04e4829bcce1ab34d",
      "source": "Yahoo!ニュース",
      "category": "健康保険",
      "summary": "【健康保険】 来年から徴収がスタートする予定の「子ども・子育て支援金」。独... (1000円, 6年6月, 600万円) [令和8年]",
      "importance": "低",
      "published_date": null,
      "scraped_at": "2025-07-30T19:33:16.880611",
      "keywords": [
        "1000円",
        "6年6月",
        "600万円",
        "250円",
        "協会けんぽ",
        "1000万円",
        "5年12月",
        "450円"
      ],
      "related_categories": [
        "社会保険全般"
      ],
      "content_length": 1335,
      "confidence_score": 1.0
    },
    {
      "id": "0030dc627786",
      "title": "2025年4月から育休給付が100％にアップすると聞きましたが、条件があると聞きました。満額で受け取るにはどうすればいいですか？…、なぜ“手取りで100％”という表現になるのでしょうか？ 育児休業中は健康保険料・厚生年金保険料が免除され、さらに勤務先から給与が支給されない場合には…ファイナンシャルフィールド経済総合7/30(水) 11:41",
      "url": "https://news.yahoo.co.jp/articles/be0d0f9c578bd221d914ae6a488361f8e551a2b8",
      "source": "Yahoo!ニュース",
      "category": "雇用保険",
      "summary": "【雇用保険】 2025年4月から育休給付が100％にアップすると聞きました... (3万円, 2023年12月, 5690円) [2025年4月]",
      "importance": "中",
      "published_date": null,
      "scraped_at": "2025-07-30T19:33:18.257375",
      "keywords": [
        "3万円",
        "2023年12月",
        "5690円",
        "2025年4月",
        "67%"
      ],
      "related_categories": [
        "健康保険",
        "厚生年金",
        "社会保険全般"
      ],
      "content_length": 1162,
      "confidence_score": 1.0
    },
    {
      "id": "a157458d34b5",
      "title": "「雇用調整助成金」の不正受給ワーストは愛知県 6月末で累計1,764件 業種別の最多は飲食業…は1,026件で約6割（構成比58.1％）を占めた。パートタイマー等の雇用保険被保険者でない従業員の休業に支給される「緊急雇用安定助成金」のみは236件（同13…東京商工リサーチ経済総合7/30(水) 13:34",
      "url": "https://news.yahoo.co.jp/articles/8d969377d11059d8f026b23df123dca977ddba2f",
      "source": "Yahoo!ニュース",
      "category": "厚生年金",
      "summary": "【厚生年金】 「雇用調整助成金」の不正受給ワーストは愛知県 6月末で累計1... (82万円, 2024年10月, 2025年6月) [2025年6月]",
      "importance": "低",
      "published_date": null,
      "scraped_at": "2025-07-30T19:33:22.152911",
      "keywords": [
        "82万円",
        "2024年10月",
        "2025年6月",
        "2020年4月"
      ],
      "related_categories": [
        "雇用保険",
        "社会保険全般"
      ],
      "content_length": 847,
      "confidence_score": 0.8
    },
    {
      "id": "8eb6c02775c0",
      "title": "【65歳以上の受講者6割以上が就職】無料で学べて手当ももらえる？「公共職業訓練と求職者支援訓練」とは？…。 公共職業訓練（離職者訓練）とは？雇用保険受給者向けの無料訓練制度公共職業訓練（離職者訓練）は、主に雇用保険を受給している、または受給資格のある離…LIMO経済総合7/30(水) 12:06",
      "url": "https://news.yahoo.co.jp/articles/1b68462b4705f1d0f4b105d20cffb4219403b64e",
      "source": "Yahoo!ニュース",
      "category": "雇用保険",
      "summary": "【雇用保険】 【65歳以上の受講者6割以上が就職】無料で学べて手当ももらえ... (500円) [令和5年]",
      "importance": "低",
      "published_date": null,
      "scraped_at": "2025-07-30T19:33:23.488393",
      "keywords": [
        "500円",
        "厚生労働省"
      ],
      "related_categories": [
        "厚生年金"
      ],
      "content_length": 1305,
      "confidence_score": 0.5333333333333333
    },
    {
      "id": "5d0125972d68",
      "title": "「育休取得者の36％が男性」過去最高に…韓国・中小企業勤務は今も“遠慮ムード”…政統計」によると、今年1月から6月までに育児休業給付金を初めて受給した雇用保険加入者は9万5064人で、前年同期（6万9631人）から37.4％増加した。KOREA WAVE韓国・北朝鮮7/30(水) 10:06",
      "url": "https://news.yahoo.co.jp/articles/57294b7de46588b0d5541c1e0c1f5840cad24c44",
      "source": "Yahoo!ニュース",
      "category": "雇用保険",
      "summary": "【雇用保険】 「育休取得者の36％が男性」過去最高に…韓国・中小企業勤務は... (34万円) [07月30日]",
      "importance": "高",
      "published_date": null,
      "scraped_at": "2025-07-30T19:33:24.945415",
      "keywords": [
        "34万円"
      ],
      "related_categories": [
        "厚生年金"
      ],
      "content_length": 978,
      "confidence_score": 0.6666666666666666
    },
    {
      "id": "d85aa6783ce2",
      "title": "女性にわいせつ行為、ハローワークで…職員の男逮捕、体を触った疑い 数年前から面識あった2人、個室で相談中に襲いかかる「抱き付いたけど、触ってない」…その後、理由不明の不起訴に 同署によると、6月18日に女性の親族から「春日部市内のハローワークに雇用保険の手続きで通所していたところ、体を触られた」と署に相談があった。男と女性…埼玉新聞埼玉7/30(水) 6:13",
      "url": "https://news.yahoo.co.jp/articles/7f21de35af5f5c3d8497c66ab5baaccd6d74c793",
      "source": "Yahoo!ニュース",
      "category": "雇用保険",
      "summary": "【雇用保険】 女性にわいせつ行為、ハローワークで…職員の男逮捕、体を触った... [5月22日]",
      "importance": "低",
      "published_date": null,
      "scraped_at": "2025-07-30T19:33:26.343190",
      "keywords": [],
      "related_categories": [],
      "content_length": 439,
      "confidence_score": 0.26666666666666666
    },
    {
      "id": "c2459686b232",
      "title": "繰上げ受給後に再就職して厚生年金加入「掛けた分が全然増えません」62歳女性の困惑…かなか見つからず、見つかったのは社会保険（厚生年金保険・健康保険）にも雇用保険にも入れない短時間勤務の仕事ばかりでした。これで少しは収入が得られるよう…Finasee経済総合7/29(火) 16:47",
      "url": "https://news.yahoo.co.jp/articles/f0b530c46fd7610705af503b04f5e3921969eecf",
      "source": "Yahoo!ニュース",
      "category": "厚生年金",
      "summary": "【厚生年金】 繰上げ受給後に再就職して厚生年金加入「掛けた分が全然増えませ... (年金事務所)",
      "importance": "低",
      "published_date": null,
      "scraped_at": "2025-07-30T19:33:27.749775",
      "keywords": [
        "年金事務所"
      ],
      "related_categories": [
        "健康保険",
        "雇用保険",
        "社会保険全般"
      ],
      "content_length": 1402,
      "confidence_score": 1.0
    },
    {
      "id": "c3e73aff825e",
      "title": "50代からの親の介護で“やってはいけないこと”とは？FPが警鐘を鳴らすワケ…2人以上なら最大10日まで休暇を取ることが可能です。正社員だけでなく、雇用保険に加入して一定期間働いているパートやアルバイトの方も使えます。2025年…女子SPA！ライフ総合7/28(月) 8:46",
      "url": "https://news.yahoo.co.jp/articles/a8aad9d0696f59708c56936b37d7fabcdfae594e",
      "source": "Yahoo!ニュース",
      "category": "雇用保険",
      "summary": "【雇用保険】 50代からの親の介護で“やってはいけないこと”とは？FPが警... (2025年4月) [2025年4月]",
      "importance": "低",
      "published_date": null,
      "scraped_at": "2025-07-30T19:33:29.145035",
      "keywords": [
        "2025年4月"
      ],
      "related_categories": [
        "社会保険全般"
      ],
      "content_length": 1293,
      "confidence_score": 0.26666666666666666
    },
    {
      "id": "cccaf1ce0bdb",
      "title": "「会社が払ってくれる」は本当か 年収400万円の人が背負う38％の実質負担の正体…大きく「保険料方式」と「税方式」がある。日本では、健康保険・厚生年金・雇用保険・労災保険・介護保険などの社会保険が主に保険料方式で運営されており、その…遠藤司経済総合7/28(月) 7:30",
      "url": "https://news.yahoo.co.jp/expert/articles/ad813b42a46a9ad31aaa90748ba983600baceea6",
      "source": "Yahoo!ニュース",
      "category": "健康保険",
      "summary": "【健康保険】 「会社が払ってくれる」は本当か 年収400万円の人が背負う3... (400万円)",
      "importance": "低",
      "published_date": null,
      "scraped_at": "2025-07-30T19:33:30.551426",
      "keywords": [
        "400万円"
      ],
      "related_categories": [
        "厚生年金",
        "雇用保険",
        "労災保険",
        "介護保険",
        "社会保険全般"
      ],
      "content_length": 0,
      "confidence_score": 0.13333333333333333
    },
    {
      "id": "b76034668e9e",
      "title": "定年退職したら「失業保険」はもらえない？「65歳前」の退職で受給できるケースはありますか？…の退職で受け取れる可能性があるのは、失業保険と呼ばれる雇用保険の基本手当ではありません。雇用保険では、満65歳に達した日を境として保険者の区分が変わる…ファイナンシャルフィールドライフ総合7/27(日) 8:10",
      "url": "https://news.yahoo.co.jp/articles/04445d7d6e560f05c7d1f47b96d59807168218f1",
      "source": "Yahoo!ニュース",
      "category": "雇用保険",
      "summary": "【雇用保険】 定年退職したら「失業保険」はもらえない？「65歳前」の退職で... (8万円)",
      "importance": "低",
      "published_date": null,
      "scraped_at": "2025-07-30T19:33:31.901821",
      "keywords": [
        "8万円"
      ],
      "related_categories": [
        "厚生年金",
        "社会保険全般"
      ],
      "content_length": 1334,
      "confidence_score": 0.9333333333333332
    },
    {
      "id": "9fe148e90b52",
      "title": "終の棲家にできる？値段や入るための条件や「こんなはずじゃなかった…」まで！安心して暮らせるシニアの住まい「サ高住」のリアル…なっています（外部と言っても、サ高住の約4分の3にはデイサービスなどの介護保険事業所や診療所が併設されています）。なお、重度の要介護者や認知症を発症し…webマガジン mi-molletライフ総合7/30(水) 20:33",
      "url": "https://news.yahoo.co.jp/articles/d7ab1477fa63d78022e65fca6f69cd01339a136b",
      "source": "Yahoo!ニュース",
      "category": "介護保険",
      "summary": "【介護保険】 終の棲家にできる？値段や入るための条件や「こんなはずじゃなか... (30万円, 2025年6月) [2025年6月]",
      "importance": "高",
      "published_date": null,
      "scraped_at": "2025-07-30T19:33:35.810684",
      "keywords": [
        "30万円",
        "2025年6月"
      ],
      "related_categories": [
        "社会保険全般"
      ],
      "content_length": 1585,
      "confidence_score": 0.7666666666666666
    },
    {
      "id": "a870cf48a562",
      "title": "【津波関連情報】「青森市役所」市役所駅前庁舎の1階で5つの課が一時窓口業務停止 駅ビル「ラビナ」では1階のテナントの従業員や利用客が2階以上に避難…青森市によりますと、午後0時15分現在、市役所駅前庁舎では1階にある市民課や介護保険課など5つの課が一時窓口業務を停止。職員や利用者が2階以上に避難したとい…ＡＴＶ青森テレビ青森7/30(水) 13:39",
      "url": "https://news.yahoo.co.jp/articles/1320196adbd62d324ce9799070edd29f425c036e",
      "source": "Yahoo!ニュース",
      "category": "介護保険",
      "summary": "【介護保険】 【津波関連情報】「青森市役所」市役所駅前庁舎の1階で5つの課...",
      "importance": "低",
      "published_date": null,
      "scraped_at": "2025-07-30T19:33:37.160463",
      "keywords": [],
      "related_categories": [],
      "content_length": 287,
      "confidence_score": 0.26666666666666666
    },
    {
      "id": "7d8f2ef46479",
      "title": "これを間違えると親子関係が悪化することが多い…FPは知っている「親の介護で絶対手を出してはいけないもの」…んが出しました。その後、介護認定を受けている人であれば改修費用の一部が介護保険から支給されることを知った穴水さん。しかし申請すると、自治体から、「改修…プレジデントオンライン経済総合7/30(水) 10:16",
      "url": "https://news.yahoo.co.jp/articles/56bfcd736176594367f571345fded1517901c8f9",
      "source": "Yahoo!ニュース",
      "category": "介護保険",
      "summary": "【介護保険】 これを間違えると親子関係が悪化することが多い…FPは知ってい... (10万円, 13万円, 5万円)",
      "importance": "中",
      "published_date": null,
      "scraped_at": "2025-07-30T19:33:38.503506",
      "keywords": [
        "10万円",
        "13万円",
        "5万円"
      ],
      "related_categories": [],
      "content_length": 1119,
      "confidence_score": 0.2333333333333333
    },
    {
      "id": "8be44d6d3a4d",
      "title": "通帳をみて心臓が止まるかと思った…「年金月28万円・貯金3,500万円」だったのに、定年9年後に夫急逝（享年69）→妻が「遺された50万円」で通夜も告別式もナシ“寂しすぎる葬式”を挙げざるを得なかったワケ…病は精神的にも経済的にも大きな負担となるため、妻名義の医療保険や民間の介護保険、そして十分な貯蓄を用意しておくことが、未来の安心に繋がるだろう。 この…THE GOLD ONLINE（ゴールドオンライン）経済総合7/30(水) 9:32",
      "url": "https://news.yahoo.co.jp/articles/bb51459004e40a7985e605a31c15ddbeabc41882",
      "source": "Yahoo!ニュース",
      "category": "健康保険",
      "summary": "【健康保険】 通帳をみて心臓が止まるかと思った…「年金月28万円・貯金3,... (50万円, 28万円, 500万円) [令和5年]",
      "importance": "低",
      "published_date": null,
      "scraped_at": "2025-07-30T19:33:39.854935",
      "keywords": [
        "50万円",
        "28万円",
        "500万円",
        "厚生労働省"
      ],
      "related_categories": [
        "厚生年金",
        "介護保険"
      ],
      "content_length": 1357,
      "confidence_score": 0.13333333333333333
    },
    {
      "id": "f528847f9264",
      "title": "【最新研究】要介護高齢者のQOL向上には「寒暖」より≪明るさ・におい≫対策がカギ！ 安価で始められる、理想の住宅環境づくりとは？…。 ■安価で始められる照明・におい対策、おすすめは 厚生労働省は、介護保険において要支援、要介護の認定を受けた人の一定の住宅改修に対し補助金を設け…東洋経済オンラインライフ総合7/30(水) 8:32",
      "url": "https://news.yahoo.co.jp/articles/634ab601444ec2850c828bb47a0f8fe9e429f579",
      "source": "Yahoo!ニュース",
      "category": "介護保険",
      "summary": "【介護保険】 【最新研究】要介護高齢者のQOL向上には「寒暖」より≪明るさ...",
      "importance": "低",
      "published_date": null,
      "scraped_at": "2025-07-30T19:33:41.315036",
      "keywords": [
        "厚生労働省"
      ],
      "related_categories": [],
      "content_length": 1070,
      "confidence_score": 0.9333333333333333
    },
    {
      "id": "8cfe91cb7b70",
      "title": "年１０万人の「介護離職」どう防ぐ…仕事と両立できる「環境づくり」実践へ国が企業向け指針…通じて企業に実践を促すことにした。 社員に「自分で介護をしすぎず、介護保険サービスを利用する」よう呼びかけることや、面談時のチェックシートを通じ介…読売新聞オンライン社会7/29(火) 19:32",
      "url": "https://news.yahoo.co.jp/articles/f5ba2b979b5946dc831e5ffeceff72d4bc561f38",
      "source": "Yahoo!ニュース",
      "category": "介護保険",
      "summary": "【介護保険】 年１０万人の「介護離職」どう防ぐ…仕事と両立できる「環境づく... (２２年１月, ２０２１年６月, ２２年９月) [２０２１年６月]",
      "importance": "中",
      "published_date": null,
      "scraped_at": "2025-07-30T19:33:42.685112",
      "keywords": [
        "２２年１月",
        "２０２１年６月",
        "２２年９月",
        "厚生労働省"
      ],
      "related_categories": [],
      "content_length": 854,
      "confidence_score": 0.13333333333333333
    },
    {
      "id": "5657fd9e3b28",
      "title": "「家庭に入って家事や育児を頑張りたかった」本音にヒット…参政党の求心力の背景にある「女性の潜在的ニーズ」…されるようになり、しかもやたら長生きなので男性以上にたっぷり社会保険や介護保険を享受してあの世に逝くもんだから、世間からの風当たりはじわじわと強まっていく。プレジデントオンライン政治7/29(火) 18:17",
      "url": "https://news.yahoo.co.jp/articles/40a81177c6499243411cd4d9c7434c9d1e97ca17",
      "source": "Yahoo!ニュース",
      "category": "社会保険全般",
      "summary": "【社会保険全般】 「家庭に入って家事や育児を頑張りたかった」本音にヒット…参政... (2025年7月) [2025年7月]",
      "importance": "低",
      "published_date": null,
      "scraped_at": "2025-07-30T19:33:44.085835",
      "keywords": [
        "2025年7月"
      ],
      "related_categories": [
        "介護保険"
      ],
      "content_length": 1011,
      "confidence_score": 0.26666666666666666
    },
    {
      "id": "3ab020c908d4",
      "title": "【75歳からの医療費】2割負担になる人の年金収入はどれくらい？《後期高齢者医療制度》判定基準を解説…外来医療費の負担が実質的に増加する可能性があります。 加えて、物価高や介護保険料の引き上げといった社会的な変化も重なり、高齢者世帯の家計はますます厳しさを増しています。LIMO経済総合7/29(火) 18:13",
      "url": "https://news.yahoo.co.jp/articles/cec61ccc580b42a594e3e24b3b18a9bddd1835dc",
      "source": "Yahoo!ニュース",
      "category": "健康保険",
      "summary": "【健康保険】 【75歳からの医療費】2割負担になる人の年金収入はどれくらい... (2025年10月, 3000円, 2025年9月) [2025年10月]",
      "importance": "中",
      "published_date": null,
      "scraped_at": "2025-07-30T19:33:45.429681",
      "keywords": [
        "2025年10月",
        "3000円",
        "2025年9月",
        "2022年10月",
        "協会けんぽ"
      ],
      "related_categories": [
        "介護保険",
        "社会保険全般"
      ],
      "content_length": 1181,
      "confidence_score": 0.5666666666666667
    },
    {
      "id": "ff624b7bb0ca",
      "title": "岡山で一人暮らしの母が要介護に…どうする？ 頼りは「チーム」 ケアマネを軸に見守り体制つくる…あって一人暮らしなら、なおさらです。住み慣れた自宅で生活を続けるには、介護保険サービスなどを活用した見守りの体制作りがカギを握ります。（野島正徳） …読売新聞（ヨミドクター）科学7/29(火) 18:04",
      "url": "https://news.yahoo.co.jp/articles/3e9be62927d0720056da83a31b55550399dd703f",
      "source": "Yahoo!ニュース",
      "category": "介護保険",
      "summary": "【介護保険】 岡山で一人暮らしの母が要介護に…どうする？ 頼りは「チーム」... [6月4日]",
      "importance": "低",
      "published_date": null,
      "scraped_at": "2025-07-30T19:33:46.802221",
      "keywords": [],
      "related_categories": [],
      "content_length": 1144,
      "confidence_score": 0.4666666666666666
    }
  ]
}